[{"cp":6016,"name":"KHMER LETTER KA","block":"Khmer","script":"Unknown","category":"Lo","kind":"glyph"},{"cp":6017,"name":"KHMER LETTER KHA","block":"Khmer","script":"Unknown","category":"Lo","kind":"glyph"},{"cp":6018,"name":"KHMER LETTER KO","block":"Khmer","script":"Unknown","category":"Lo","kind":"glyph"},{"cp":6019,"name":"KHMER LETTER KHO","block":"Khmer","script":"Unknown","category":"Lo","kind":"glyph"},{"cp":6020,"name":"KHMER LETTER NGO","block":"Khmer","script":"Unknown","category":"Lo","kind":"glyph"},{"cp":6021,"name":"KHMER LETTER CA","block":"Khmer","script":"Unknown","category":"Lo","kind":"glyph"},{"cp":6022,"name":"KHMER LETTER CHA","block":"Khmer","script":"Unknown","category":"Lo","kind":"glyph"},{"cp":6023,"name":"KHMER LETTER CO","block":"Khmer","script":"Unknown","category":"Lo","kind":"glyph"},{"cp":6024,"name":"KHMER LETTER CHO","block":"Khmer","script":"Unknown","category":"Lo","kind":"glyph"},{"cp":6025,"name":"KHMER LETTER NYO","block":"Khmer","script":"Unknown","category":"Lo","kind":"glyph"},{"cp":6026,"name":"KHMER LETTER DA","block":"Khmer","script":"Unknown","category":"Lo","kind":"glyph"},{"cp":6027,"name":"KHMER LETTER TTHA","block":"Khmer","script":"Unknown","category":"Lo","kind":"glyph"},{"cp":6028,"name":"KHMER LETTER DO","block":"Khmer","script":"Unknown","category":"Lo","kind":"glyph"},{"cp":6029,"name":"KHMER LETTER TTHO","block":"Khmer","script":"Unknown","category":"Lo","kind":"glyph"},{"cp":6030,"name":"KHMER LETTER NNO","block":"Khmer","script":"Unknown","category":"Lo","kind":"glyph"},{"cp":6031,"name":"KHMER LETTER TA","block":"Khmer","script":"Unknown","category":"Lo","kind":"glyph"},{"cp":6032,"name":"KHMER LETTER THA","block":"Khmer","script":"Unknown","category":"Lo","kind":"glyph"},{"cp":6033,"name":"KHMER LETTER TO","block":"Khmer","script":"Unknown","category":"Lo","kind":"glyph"},{"cp":6034,"name":"KHMER LETTER THO","block":"Khmer","script":"Unknown","category":"Lo","kind":"glyph"},{"cp":6035,"name":"KHMER LETTER NO","block":"Khmer","script":"Unknown","category":"Lo","kind":"glyph"},{"cp":6036,"name":"KHMER LETTER BA","block":"Khmer","script":"Unknown","category":"Lo","kind":"glyph"},{"cp":6037,"name":"KHMER LETTER PHA","block":"Khmer","script":"Unknown","category":"Lo","kind":"glyph"},{"cp":6038,"name":"KHMER LETTER PO","block":"Khmer","script":"Unknown","category":"Lo","kind":"glyph"},{"cp":6039,"name":"KHMER LETTER PHO","block":"Khmer","script":"Unknown","category":"Lo","kind":"glyph"},{"cp":6040,"name":"KHMER LETTER MO","block":"Khmer","script":"Unknown","category":"Lo","kind":"glyph"},{"cp":6041,"name":"KHMER LETTER YO","block":"Khmer","script":"Unknown","category":"Lo","kind":"glyph"},{"cp":6042,"name":"KHMER LETTER RO","block":"Khmer","script":"Unknown","category":"Lo","kind":"glyph"},{"cp":6043,"name":"KHMER LETTER LO","block":"Khmer","script":"Unknown","category":"Lo","kind":"glyph"},{"cp":6044,"name":"KHMER LETTER VO","block":"Khmer","script":"Unknown","category":"Lo","kind":"glyph"},{"cp":6045,"name":"KHMER LETTER SHA","block":"Khmer","script":"Unknown","category":"Lo","kind":"glyph"},{"cp":6046,"name":"KHMER LETTER SSO","block":"Khmer","script":"Unknown","category":"Lo","kind":"glyph"},{"cp":6047,"name":"KHMER LETTER SA","block":"Khmer","script":"Unknown","category":"Lo","kind":"glyph"},{"cp":6048,"name":"KHMER LETTER HA","block":"Khmer","script":"Unknown","category":"Lo","kind":"glyph"},{"cp":6049,"name":"KHMER LETTER LA","block":"Khmer","script":"Unknown","category":"Lo","kind":"glyph"},{"cp":6050,"name":"KHMER LETTER QA","block":"Khmer","script":"Unknown","category":"Lo","kind":"glyph"},{"cp":6051,"name":"KHMER INDEPENDENT VOWEL QAQ","block":"Khmer","script":"Unknown","category":"Lo","kind":"glyph"},{"cp":6052,"name":"KHMER INDEPENDENT VOWEL QAA","block":"Khmer","script":"Unknown","category":"Lo","kind":"glyph"},{"cp":6053,"name":"KHMER INDEPENDENT VOWEL QI","block":"Khmer","script":"Unknown","category":"Lo","kind":"glyph"},{"cp":6054,"name":"KHMER INDEPENDENT VOWEL QII","block":"Khmer","script":"Unknown","category":"Lo","kind":"glyph"},{"cp":6055,"name":"KHMER INDEPENDENT VOWEL QU","block":"Khmer","script":"Unknown","category":"Lo","kind":"glyph"},{"cp":6056,"name":"KHMER INDEPENDENT VOWEL QUK","block":"Khmer","script":"Unknown","category":"Lo","kind":"glyph"},{"cp":6057,"name":"KHMER INDEPENDENT VOWEL QUU","block":"Khmer","script":"Unknown","category":"Lo","kind":"glyph"},{"cp":6058,"name":"KHMER INDEPENDENT VOWEL QUUV","block":"Khmer","script":"Unknown","category":"Lo","kind":"glyph"},{"cp":6059,"name":"KHMER INDEPENDENT VOWEL RY","block":"Khmer","script":"Unknown","category":"Lo","kind":"glyph"},{"cp":6060,"name":"KHMER INDEPENDENT VOWEL RYY","block":"Khmer","script":"Unknown","category":"Lo","kind":"glyph"},{"cp":6061,"name":"KHMER INDEPENDENT VOWEL LY","block":"Khmer","script":"Unknown","category":"Lo","kind":"glyph"},{"cp":6062,"name":"KHMER INDEPENDENT VOWEL LYY","block":"Khmer","script":"Unknown","category":"Lo","kind":"glyph"},{"cp":6063,"name":"KHMER INDEPENDENT VOWEL QE","block":"Khmer","script":"Unknown","category":"Lo","kind":"glyph"},{"cp":6064,"name":"KHMER INDEPENDENT VOWEL QAI","block":"Khmer","script":"Unknown","category":"Lo","kind":"glyph"},{"cp":6065,"name":"KHMER INDEPENDENT VOWEL QOO TYPE ONE","block":"Khmer","script":"Unknown","category":"Lo","kind":"glyph"},{"cp":6066,"name":"KHMER INDEPENDENT VOWEL QOO TYPE TWO","block":"Khmer","script":"Unknown","category":"Lo","kind":"glyph"},{"cp":6067,"name":"KHMER INDEPENDENT VOWEL QAU","block":"Khmer","script":"Unknown","category":"Lo","kind":"glyph"},{"cp":6068,"name":"KHMER VOWEL INHERENT AQ","block":"Khmer","script":"Unknown","category":"Mn","description":"A combining mark that attaches to a preceding base character rather than standing alone.","kind":"combining","keywords":["combining mark"]},{"cp":6069,"name":"KHMER VOWEL INHERENT AA","block":"Khmer","script":"Unknown","category":"Mn","description":"A combining mark that attaches to a preceding base character rather than standing alone.","kind":"combining","keywords":["combining mark"]},{"cp":6070,"name":"KHMER VOWEL SIGN AA","block":"Khmer","script":"Unknown","category":"Mc","description":"A combining mark that attaches to a preceding base character rather than standing alone.","kind":"combining","keywords":["combining mark"]},{"cp":6071,"name":"KHMER VOWEL SIGN I","block":"Khmer","script":"Unknown","category":"Mn","description":"A combining mark that attaches to a preceding base character rather than standing alone.","kind":"combining","keywords":["combining mark"]},{"cp":6072,"name":"KHMER VOWEL SIGN II","block":"Khmer","script":"Unknown","category":"Mn","description":"A combining mark that attaches to a preceding base character rather than standing alone.","kind":"combining","keywords":["combining mark"]},{"cp":6073,"name":"KHMER VOWEL SIGN Y","block":"Khmer","script":"Unknown","category":"Mn","description":"A combining mark that attaches to a preceding base character rather than standing alone.","kind":"combining","keywords":["combining mark"]},{"cp":6074,"name":"KHMER VOWEL SIGN YY","block":"Khmer","script":"Unknown","category":"Mn","description":"A combining mark that attaches to a preceding base character rather than standing alone.","kind":"combining","keywords":["combining mark"]},{"cp":6075,"name":"KHMER VOWEL SIGN U","block":"Khmer","script":"Unknown","category":"Mn","description":"A combining mark that attaches to a preceding base character rather than standing alone.","kind":"combining","keywords":["combining mark"]},{"cp":6076,"name":"KHMER VOWEL SIGN UU","block":"Khmer","script":"Unknown","category":"Mn","description":"A combining mark that attaches to a preceding base character rather than standing alone.","kind":"combining","keywords":["combining mark"]},{"cp":6077,"name":"KHMER VOWEL SIGN UA","block":"Khmer","script":"Unknown","category":"Mn","description":"A combining mark that attaches to a preceding base character rather than standing alone.","kind":"combining","keywords":["combining mark"]},{"cp":6078,"name":"KHMER VOWEL SIGN OE","block":"Khmer","script":"Unknown","category":"Mc","description":"A combining mark that attaches to a preceding base character rather than standing alone.","kind":"combining","keywords":["combining mark"]},{"cp":6079,"name":"KHMER VOWEL SIGN YA","block":"Khmer","script":"Unknown","category":"Mc","description":"A combining mark that attaches to a preceding base character rather than standing alone.","kind":"combining","keywords":["combining mark"]},{"cp":6080,"name":"KHMER VOWEL SIGN IE","block":"Khmer","script":"Unknown","category":"Mc","description":"A combining mark that attaches to a preceding base character rather than standing alone.","kind":"combining","keywords":["combining mark"]},{"cp":6081,"name":"KHMER VOWEL SIGN E","block":"Khmer","script":"Unknown","category":"Mc","description":"A combining mark that attaches to a preceding base character rather than standing alone.","kind":"combining","keywords":["combining mark"]},{"cp":6082,"name":"KHMER VOWEL SIGN AE","block":"Khmer","script":"Unknown","category":"Mc","description":"A combining mark that attaches to a preceding base character rather than standing alone.","kind":"combining","keywords":["combining mark"]},{"cp":6083,"name":"KHMER VOWEL SIGN AI","block":"Khmer","script":"Unknown","category":"Mc","description":"A combining mark that attaches to a preceding base character rather than standing alone.","kind":"combining","keywords":["combining mark"]},{"cp":6084,"name":"KHMER VOWEL SIGN OO","block":"Khmer","script":"Unknown","category":"Mc","description":"A combining mark that attaches to a preceding base character rather than standing alone.","kind":"combining","keywords":["combining mark"]},{"cp":6085,"name":"KHMER VOWEL SIGN AU","block":"Khmer","script":"Unknown","category":"Mc","description":"A combining mark that attaches to a preceding base character rather than standing alone.","kind":"combining","keywords":["combining mark"]},{"cp":6086,"name":"KHMER SIGN NIKAHIT","block":"Khmer","script":"Unknown","category":"Mn","description":"A combining mark that attaches to a preceding base character rather than standing alone.","kind":"combining","keywords":["combining mark"]},{"cp":6087,"name":"KHMER SIGN REAHMUK","block":"Khmer","script":"Unknown","category":"Mc","description":"A combining mark that attaches to a preceding base character rather than standing alone.","kind":"combining","keywords":["combining mark"]},{"cp":6088,"name":"KHMER SIGN YUUKALEAPINTU","block":"Khmer","script":"Unknown","category":"Mc","description":"A combining mark that attaches to a preceding base character rather than standing alone.","kind":"combining","keywords":["combining mark"]},{"cp":6089,"name":"KHMER SIGN MUUSIKATOAN","block":"Khmer","script":"Unknown","category":"Mn","description":"A combining mark that attaches to a preceding base character rather than standing alone.","kind":"combining","keywords":["combining mark"]},{"cp":6090,"name":"KHMER SIGN TRIISAP","block":"Khmer","script":"Unknown","category":"Mn","description":"A combining mark that attaches to a preceding base character rather than standing alone.","kind":"combining","keywords":["combining mark"]},{"cp":6091,"name":"KHMER SIGN BANTOC","block":"Khmer","script":"Unknown","category":"Mn","description":"A combining mark that attaches to a preceding base character rather than standing alone.","kind":"combining","keywords":["combining mark"]},{"cp":6092,"name":"KHMER SIGN ROBAT","block":"Khmer","script":"Unknown","category":"Mn","description":"A combining mark that attaches to a preceding base character rather than standing alone.","kind":"combining","keywords":["combining mark"]},{"cp":6093,"name":"KHMER SIGN TOANDAKHIAT","block":"Khmer","script":"Unknown","category":"Mn","description":"A combining mark that attaches to a preceding base character rather than standing alone.","kind":"combining","keywords":["combining mark"]},{"cp":6094,"name":"KHMER SIGN KAKABAT","block":"Khmer","script":"Unknown","category":"Mn","description":"A combining mark that attaches to a preceding base character rather than standing alone.","kind":"combining","keywords":["combining mark"]},{"cp":6095,"name":"KHMER SIGN AHSDA","block":"Khmer","script":"Unknown","category":"Mn","description":"A combining mark that attaches to a preceding base character rather than standing alone.","kind":"combining","keywords":["combining mark"]},{"cp":6096,"name":"KHMER SIGN SAMYOK SANNYA","block":"Khmer","script":"Unknown","category":"Mn","description":"A combining mark that attaches to a preceding base character rather than standing alone.","kind":"combining","keywords":["combining mark"]},{"cp":6097,"name":"KHMER SIGN VIRIAM","block":"Khmer","script":"Unknown","category":"Mn","description":"A combining mark that attaches to a preceding base character rather than standing alone.","kind":"combining","keywords":["combining mark"]},{"cp":6098,"name":"KHMER SIGN COENG","block":"Khmer","script":"Unknown","category":"Mn","description":"A combining mark that attaches to a preceding base character rather than standing alone.","kind":"combining","keywords":["combining mark"]},{"cp":6099,"name":"KHMER SIGN BATHAMASAT","block":"Khmer","script":"Unknown","category":"Mn","description":"A combining mark that attaches to a preceding base character rather than standing alone.","kind":"combining","keywords":["combining mark"]},{"cp":6100,"name":"KHMER SIGN KHAN","block":"Khmer","script":"Unknown","category":"Po","kind":"glyph"},{"cp":6101,"name":"KHMER SIGN BARIYOOSAN","block":"Khmer","script":"Unknown","category":"Po","kind":"glyph"},{"cp":6102,"name":"KHMER SIGN CAMNUC PII KUUH","block":"Khmer","script":"Unknown","category":"Po","kind":"glyph"},{"cp":6103,"name":"KHMER SIGN LEK TOO","block":"Khmer","script":"Unknown","category":"Lm","kind":"glyph"},{"cp":6104,"name":"KHMER SIGN BEYYAL","block":"Khmer","script":"Unknown","category":"Po","kind":"glyph"},{"cp":6105,"name":"KHMER SIGN PHNAEK MUAN","block":"Khmer","script":"Unknown","category":"Po","kind":"glyph"},{"cp":6106,"name":"KHMER SIGN KOOMUUT","block":"Khmer","script":"Unknown","category":"Po","kind":"glyph"},{"cp":6107,"name":"KHMER CURRENCY SYMBOL RIEL","block":"Khmer","script":"Unknown","category":"Sc","kind":"glyph"},{"cp":6108,"name":"KHMER SIGN AVAKRAHASANYA","block":"Khmer","script":"Unknown","category":"Lo","kind":"glyph"},{"cp":6109,"name":"KHMER SIGN ATTHACAN","block":"Khmer","script":"Unknown","category":"Mn","description":"A combining mark that attaches to a preceding base character rather than standing alone.","kind":"combining","keywords":["combining mark"]},{"cp":6112,"name":"KHMER DIGIT ZERO","block":"Khmer","script":"Unknown","category":"Nd","kind":"glyph"},{"cp":6113,"name":"KHMER DIGIT ONE","block":"Khmer","script":"Unknown","category":"Nd","kind":"glyph"},{"cp":6114,"name":"KHMER DIGIT TWO","block":"Khmer","script":"Unknown","category":"Nd","kind":"glyph"},{"cp":6115,"name":"KHMER DIGIT THREE","block":"Khmer","script":"Unknown","category":"Nd","kind":"glyph"},{"cp":6116,"name":"KHMER DIGIT FOUR","block":"Khmer","script":"Unknown","category":"Nd","kind":"glyph"},{"cp":6117,"name":"KHMER DIGIT FIVE","block":"Khmer","script":"Unknown","category":"Nd","kind":"glyph"},{"cp":6118,"name":"KHMER DIGIT SIX","block":"Khmer","script":"Unknown","category":"Nd","kind":"glyph"},{"cp":6119,"name":"KHMER DIGIT SEVEN","block":"Khmer","script":"Unknown","category":"Nd","kind":"glyph"},{"cp":6120,"name":"KHMER DIGIT EIGHT","block":"Khmer","script":"Unknown","category":"Nd","kind":"glyph"},{"cp":6121,"name":"KHMER DIGIT NINE","block":"Khmer","script":"Unknown","category":"Nd","kind":"glyph"},{"cp":6128,"name":"KHMER SYMBOL LEK ATTAK SON","block":"Khmer","script":"Unknown","category":"No","kind":"glyph"},{"cp":6129,"name":"KHMER SYMBOL LEK ATTAK MUOY","block":"Khmer","script":"Unknown","category":"No","kind":"glyph"},{"cp":6130,"name":"KHMER SYMBOL LEK ATTAK PII","block":"Khmer","script":"Unknown","category":"No","kind":"glyph"},{"cp":6131,"name":"KHMER SYMBOL LEK ATTAK BEI","block":"Khmer","script":"Unknown","category":"No","kind":"glyph"},{"cp":6132,"name":"KHMER SYMBOL LEK ATTAK BUON","block":"Khmer","script":"Unknown","category":"No","kind":"glyph"},{"cp":6133,"name":"KHMER SYMBOL LEK ATTAK PRAM","block":"Khmer","script":"Unknown","category":"No","kind":"glyph"},{"cp":6134,"name":"KHMER SYMBOL LEK ATTAK PRAM-MUOY","block":"Khmer","script":"Unknown","category":"No","kind":"glyph"},{"cp":6135,"name":"KHMER SYMBOL LEK ATTAK PRAM-PII","block":"Khmer","script":"Unknown","category":"No","kind":"glyph"},{"cp":6136,"name":"KHMER SYMBOL LEK ATTAK PRAM-BEI","block":"Khmer","script":"Unknown","category":"No","kind":"glyph"},{"cp":6137,"name":"KHMER SYMBOL LEK ATTAK PRAM-BUON","block":"Khmer","script":"Unknown","category":"No","kind":"glyph"}]
