[{"cp":10496,"name":"RIGHTWARDS TWO-HEADED ARROW WITH VERTICAL STROKE","block":"Supplemental Arrows-B","script":"Unknown","category":"Sm","kind":"glyph"},{"cp":10497,"name":"RIGHTWARDS TWO-HEADED ARROW WITH DOUBLE VERTICAL STROKE","block":"Supplemental Arrows-B","script":"Unknown","category":"Sm","kind":"glyph"},{"cp":10498,"name":"LEFTWARDS DOUBLE ARROW WITH VERTICAL STROKE","block":"Supplemental Arrows-B","script":"Unknown","category":"Sm","kind":"glyph"},{"cp":10499,"name":"RIGHTWARDS DOUBLE ARROW WITH VERTICAL STROKE","block":"Supplemental Arrows-B","script":"Unknown","category":"Sm","kind":"glyph"},{"cp":10500,"name":"LEFT RIGHT DOUBLE ARROW WITH VERTICAL STROKE","block":"Supplemental Arrows-B","script":"Unknown","category":"Sm","kind":"glyph"},{"cp":10501,"name":"RIGHTWARDS TWO-HEADED ARROW FROM BAR","block":"Supplemental Arrows-B","script":"Unknown","category":"Sm","kind":"glyph"},{"cp":10502,"name":"LEFTWARDS DOUBLE ARROW FROM BAR","block":"Supplemental Arrows-B","script":"Unknown","category":"Sm","kind":"glyph"},{"cp":10503,"name":"RIGHTWARDS DOUBLE ARROW FROM BAR","block":"Supplemental Arrows-B","script":"Unknown","category":"Sm","kind":"glyph"},{"cp":10504,"name":"DOWNWARDS ARROW WITH HORIZONTAL STROKE","block":"Supplemental Arrows-B","script":"Unknown","category":"Sm","kind":"glyph"},{"cp":10505,"name":"UPWARDS ARROW WITH HORIZONTAL STROKE","block":"Supplemental Arrows-B","script":"Unknown","category":"Sm","kind":"glyph"},{"cp":10506,"name":"UPWARDS TRIPLE ARROW","block":"Supplemental Arrows-B","script":"Unknown","category":"Sm","kind":"glyph"},{"cp":10507,"name":"DOWNWARDS TRIPLE ARROW","block":"Supplemental Arrows-B","script":"Unknown","category":"Sm","kind":"glyph"},{"cp":10508,"name":"LEFTWARDS DOUBLE DASH ARROW","block":"Supplemental Arrows-B","script":"Unknown","category":"Sm","kind":"glyph"},{"cp":10509,"name":"RIGHTWARDS DOUBLE DASH ARROW","block":"Supplemental Arrows-B","script":"Unknown","category":"Sm","kind":"glyph"},{"cp":10510,"name":"LEFTWARDS TRIPLE DASH ARROW","block":"Supplemental Arrows-B","script":"Unknown","category":"Sm","kind":"glyph"},{"cp":10511,"name":"RIGHTWARDS TRIPLE DASH ARROW","block":"Supplemental Arrows-B","script":"Unknown","category":"Sm","kind":"glyph"},{"cp":10512,"name":"RIGHTWARDS TWO-HEADED TRIPLE DASH ARROW","block":"Supplemental Arrows-B","script":"Unknown","category":"Sm","kind":"glyph"},{"cp":10513,"name":"RIGHTWARDS ARROW WITH DOTTED STEM","block":"Supplemental Arrows-B","script":"Unknown","category":"Sm","kind":"glyph"},{"cp":10514,"name":"UPWARDS ARROW TO BAR","block":"Supplemental Arrows-B","script":"Unknown","category":"Sm","kind":"glyph"},{"cp":10515,"name":"DOWNWARDS ARROW TO BAR","block":"Supplemental Arrows-B","script":"Unknown","category":"Sm","kind":"glyph"},{"cp":10516,"name":"RIGHTWARDS ARROW WITH TAIL WITH VERTICAL STROKE","block":"Supplemental Arrows-B","script":"Unknown","category":"Sm","kind":"glyph"},{"cp":10517,"name":"RIGHTWARDS ARROW WITH TAIL WITH DOUBLE VERTICAL STROKE","block":"Supplemental Arrows-B","script":"Unknown","category":"Sm","kind":"glyph"},{"cp":10518,"name":"RIGHTWARDS TWO-HEADED ARROW WITH TAIL","block":"Supplemental Arrows-B","script":"Unknown","category":"Sm","kind":"glyph"},{"cp":10519,"name":"RIGHTWARDS TWO-HEADED ARROW WITH TAIL WITH VERTICAL STROKE","block":"Supplemental Arrows-B","script":"Unknown","category":"Sm","kind":"glyph"},{"cp":10520,"name":"RIGHTWARDS TWO-HEADED ARROW WITH TAIL WITH DOUBLE VERTICAL STROKE","block":"Supplemental Arrows-B","script":"Unknown","category":"Sm","kind":"glyph"},{"cp":10521,"name":"LEFTWARDS ARROW-TAIL","block":"Supplemental Arrows-B","script":"Unknown","category":"Sm","kind":"glyph"},{"cp":10522,"name":"RIGHTWARDS ARROW-TAIL","block":"Supplemental Arrows-B","script":"Unknown","category":"Sm","kind":"glyph"},{"cp":10523,"name":"LEFTWARDS DOUBLE ARROW-TAIL","block":"Supplemental Arrows-B","script":"Unknown","category":"Sm","kind":"glyph"},{"cp":10524,"name":"RIGHTWARDS DOUBLE ARROW-TAIL","block":"Supplemental Arrows-B","script":"Unknown","category":"Sm","kind":"glyph"},{"cp":10525,"name":"LEFTWARDS ARROW TO BLACK DIAMOND","block":"Supplemental Arrows-B","script":"Unknown","category":"Sm","kind":"glyph"},{"cp":10526,"name":"RIGHTWARDS ARROW TO BLACK DIAMOND","block":"Supplemental Arrows-B","script":"Unknown","category":"Sm","kind":"glyph"},{"cp":10527,"name":"LEFTWARDS ARROW FROM BAR TO BLACK DIAMOND","block":"Supplemental Arrows-B","script":"Unknown","category":"Sm","kind":"glyph"},{"cp":10528,"name":"RIGHTWARDS ARROW FROM BAR TO BLACK DIAMOND","block":"Supplemental Arrows-B","script":"Unknown","category":"Sm","kind":"glyph"},{"cp":10529,"name":"NORTH WEST AND SOUTH EAST ARROW","block":"Supplemental Arrows-B","script":"Unknown","category":"Sm","kind":"glyph"},{"cp":10530,"name":"NORTH EAST AND SOUTH WEST ARROW","block":"Supplemental Arrows-B","script":"Unknown","category":"Sm","kind":"glyph"},{"cp":10531,"name":"NORTH WEST ARROW WITH HOOK","block":"Supplemental Arrows-B","script":"Unknown","category":"Sm","kind":"glyph"},{"cp":10532,"name":"NORTH EAST ARROW WITH HOOK","block":"Supplemental Arrows-B","script":"Unknown","category":"Sm","kind":"glyph"},{"cp":10533,"name":"SOUTH EAST ARROW WITH HOOK","block":"Supplemental Arrows-B","script":"Unknown","category":"Sm","kind":"glyph"},{"cp":10534,"name":"SOUTH WEST ARROW WITH HOOK","block":"Supplemental Arrows-B","script":"Unknown","category":"Sm","kind":"glyph"},{"cp":10535,"name":"NORTH WEST ARROW AND NORTH EAST ARROW","block":"Supplemental Arrows-B","script":"Unknown","category":"Sm","kind":"glyph"},{"cp":10536,"name":"NORTH EAST ARROW AND SOUTH EAST ARROW","block":"Supplemental Arrows-B","script":"Unknown","category":"Sm","kind":"glyph"},{"cp":10537,"name":"SOUTH EAST ARROW AND SOUTH WEST ARROW","block":"Supplemental Arrows-B","script":"Unknown","category":"Sm","kind":"glyph"},{"cp":10538,"name":"SOUTH WEST ARROW AND NORTH WEST ARROW","block":"Supplemental Arrows-B","script":"Unknown","category":"Sm","kind":"glyph"},{"cp":10539,"name":"RISING DIAGONAL CROSSING FALLING DIAGONAL","block":"Supplemental Arrows-B","script":"Unknown","category":"Sm","kind":"glyph"},{"cp":10540,"name":"FALLING DIAGONAL CROSSING RISING DIAGONAL","block":"Supplemental Arrows-B","script":"Unknown","category":"Sm","kind":"glyph"},{"cp":10541,"name":"SOUTH EAST ARROW CROSSING NORTH EAST ARROW","block":"Supplemental Arrows-B","script":"Unknown","category":"Sm","kind":"glyph"},{"cp":10542,"name":"NORTH EAST ARROW CROSSING SOUTH EAST ARROW","block":"Supplemental Arrows-B","script":"Unknown","category":"Sm","kind":"glyph"},{"cp":10543,"name":"FALLING DIAGONAL CROSSING NORTH EAST ARROW","block":"Supplemental Arrows-B","script":"Unknown","category":"Sm","kind":"glyph"},{"cp":10544,"name":"RISING DIAGONAL CROSSING SOUTH EAST ARROW","block":"Supplemental Arrows-B","script":"Unknown","category":"Sm","kind":"glyph"},{"cp":10545,"name":"NORTH EAST ARROW CROSSING NORTH WEST ARROW","block":"Supplemental Arrows-B","script":"Unknown","category":"Sm","kind":"glyph"},{"cp":10546,"name":"NORTH WEST ARROW CROSSING NORTH EAST ARROW","block":"Supplemental Arrows-B","script":"Unknown","category":"Sm","kind":"glyph"},{"cp":10547,"name":"WAVE ARROW POINTING DIRECTLY RIGHT","block":"Supplemental Arrows-B","script":"Unknown","category":"Sm","kind":"glyph"},{"cp":10548,"name":"ARROW POINTING RIGHTWARDS THEN CURVING UPWARDS","block":"Supplemental Arrows-B","script":"Unknown","category":"Sm","kind":"glyph"},{"cp":10549,"name":"ARROW POINTING RIGHTWARDS THEN CURVING DOWNWARDS","block":"Supplemental Arrows-B","script":"Unknown","category":"Sm","kind":"glyph"},{"cp":10550,"name":"ARROW POINTING DOWNWARDS THEN CURVING LEFTWARDS","block":"Supplemental Arrows-B","script":"Unknown","category":"Sm","kind":"glyph"},{"cp":10551,"name":"ARROW POINTING DOWNWARDS THEN CURVING RIGHTWARDS","block":"Supplemental Arrows-B","script":"Unknown","category":"Sm","kind":"glyph"},{"cp":10552,"name":"RIGHT-SIDE ARC CLOCKWISE ARROW","block":"Supplemental Arrows-B","script":"Unknown","category":"Sm","kind":"glyph"},{"cp":10553,"name":"LEFT-SIDE ARC ANTICLOCKWISE ARROW","block":"Supplemental Arrows-B","script":"Unknown","category":"Sm","kind":"glyph"},{"cp":10554,"name":"TOP ARC ANTICLOCKWISE ARROW","block":"Supplemental Arrows-B","script":"Unknown","category":"Sm","kind":"glyph"},{"cp":10555,"name":"BOTTOM ARC ANTICLOCKWISE ARROW","block":"Supplemental Arrows-B","script":"Unknown","category":"Sm","kind":"glyph"},{"cp":10556,"name":"TOP ARC CLOCKWISE ARROW WITH MINUS","block":"Supplemental Arrows-B","script":"Unknown","category":"Sm","kind":"glyph"},{"cp":10557,"name":"TOP ARC ANTICLOCKWISE ARROW WITH PLUS","block":"Supplemental Arrows-B","script":"Unknown","category":"Sm","kind":"glyph"},{"cp":10558,"name":"LOWER RIGHT SEMICIRCULAR CLOCKWISE ARROW","block":"Supplemental Arrows-B","script":"Unknown","category":"Sm","kind":"glyph"},{"cp":10559,"name":"LOWER LEFT SEMICIRCULAR ANTICLOCKWISE ARROW","block":"Supplemental Arrows-B","script":"Unknown","category":"Sm","kind":"glyph"},{"cp":10560,"name":"ANTICLOCKWISE CLOSED CIRCLE ARROW","block":"Supplemental Arrows-B","script":"Unknown","category":"Sm","kind":"glyph"},{"cp":10561,"name":"CLOCKWISE CLOSED CIRCLE ARROW","block":"Supplemental Arrows-B","script":"Unknown","category":"Sm","kind":"glyph"},{"cp":10562,"name":"RIGHTWARDS ARROW ABOVE SHORT LEFTWARDS ARROW","block":"Supplemental Arrows-B","script":"Unknown","category":"Sm","kind":"glyph"},{"cp":10563,"name":"LEFTWARDS ARROW ABOVE SHORT RIGHTWARDS ARROW","block":"Supplemental Arrows-B","script":"Unknown","category":"Sm","kind":"glyph"},{"cp":10564,"name":"SHORT RIGHTWARDS ARROW ABOVE LEFTWARDS ARROW","block":"Supplemental Arrows-B","script":"Unknown","category":"Sm","kind":"glyph"},{"cp":10565,"name":"RIGHTWARDS ARROW WITH PLUS BELOW","block":"Supplemental Arrows-B","script":"Unknown","category":"Sm","kind":"glyph"},{"cp":10566,"name":"LEFTWARDS ARROW WITH PLUS BELOW","block":"Supplemental Arrows-B","script":"Unknown","category":"Sm","kind":"glyph"},{"cp":10567,"name":"RIGHTWARDS ARROW THROUGH X","block":"Supplemental Arrows-B","script":"Unknown","category":"Sm","kind":"glyph"},{"cp":10568,"name":"LEFT RIGHT ARROW THROUGH SMALL CIRCLE","block":"Supplemental Arrows-B","script":"Unknown","category":"Sm","kind":"glyph"},{"cp":10569,"name":"UPWARDS TWO-HEADED ARROW FROM SMALL CIRCLE","block":"Supplemental Arrows-B","script":"Unknown","category":"Sm","kind":"glyph"},{"cp":10570,"name":"LEFT BARB UP RIGHT BARB DOWN HARPOON","block":"Supplemental Arrows-B","script":"Unknown","category":"Sm","kind":"glyph"},{"cp":10571,"name":"LEFT BARB DOWN RIGHT BARB UP HARPOON","block":"Supplemental Arrows-B","script":"Unknown","category":"Sm","kind":"glyph"},{"cp":10572,"name":"UP BARB RIGHT DOWN BARB LEFT HARPOON","block":"Supplemental Arrows-B","script":"Unknown","category":"Sm","kind":"glyph"},{"cp":10573,"name":"UP BARB LEFT DOWN BARB RIGHT HARPOON","block":"Supplemental Arrows-B","script":"Unknown","category":"Sm","kind":"glyph"},{"cp":10574,"name":"LEFT BARB UP RIGHT BARB UP HARPOON","block":"Supplemental Arrows-B","script":"Unknown","category":"Sm","kind":"glyph"},{"cp":10575,"name":"UP BARB RIGHT DOWN BARB RIGHT HARPOON","block":"Supplemental Arrows-B","script":"Unknown","category":"Sm","kind":"glyph"},{"cp":10576,"name":"LEFT BARB DOWN RIGHT BARB DOWN HARPOON","block":"Supplemental Arrows-B","script":"Unknown","category":"Sm","kind":"glyph"},{"cp":10577,"name":"UP BARB LEFT DOWN BARB LEFT HARPOON","block":"Supplemental Arrows-B","script":"Unknown","category":"Sm","kind":"glyph"},{"cp":10578,"name":"LEFTWARDS HARPOON WITH BARB UP TO BAR","block":"Supplemental Arrows-B","script":"Unknown","category":"Sm","kind":"glyph"},{"cp":10579,"name":"RIGHTWARDS HARPOON WITH BARB UP TO BAR","block":"Supplemental Arrows-B","script":"Unknown","category":"Sm","kind":"glyph"},{"cp":10580,"name":"UPWARDS HARPOON WITH BARB RIGHT TO BAR","block":"Supplemental Arrows-B","script":"Unknown","category":"Sm","kind":"glyph"},{"cp":10581,"name":"DOWNWARDS HARPOON WITH BARB RIGHT TO BAR","block":"Supplemental Arrows-B","script":"Unknown","category":"Sm","kind":"glyph"},{"cp":10582,"name":"LEFTWARDS HARPOON WITH BARB DOWN TO BAR","block":"Supplemental Arrows-B","script":"Unknown","category":"Sm","kind":"glyph"},{"cp":10583,"name":"RIGHTWARDS HARPOON WITH BARB DOWN TO BAR","block":"Supplemental Arrows-B","script":"Unknown","category":"Sm","kind":"glyph"},{"cp":10584,"name":"UPWARDS HARPOON WITH BARB LEFT TO BAR","block":"Supplemental Arrows-B","script":"Unknown","category":"Sm","kind":"glyph"},{"cp":10585,"name":"DOWNWARDS HARPOON WITH BARB LEFT TO BAR","block":"Supplemental Arrows-B","script":"Unknown","category":"Sm","kind":"glyph"},{"cp":10586,"name":"LEFTWARDS HARPOON WITH BARB UP FROM BAR","block":"Supplemental Arrows-B","script":"Unknown","category":"Sm","kind":"glyph"},{"cp":10587,"name":"RIGHTWARDS HARPOON WITH BARB UP FROM BAR","block":"Supplemental Arrows-B","script":"Unknown","category":"Sm","kind":"glyph"},{"cp":10588,"name":"UPWARDS HARPOON WITH BARB RIGHT FROM BAR","block":"Supplemental Arrows-B","script":"Unknown","category":"Sm","kind":"glyph"},{"cp":10589,"name":"DOWNWARDS HARPOON WITH BARB RIGHT FROM BAR","block":"Supplemental Arrows-B","script":"Unknown","category":"Sm","kind":"glyph"},{"cp":10590,"name":"LEFTWARDS HARPOON WITH BARB DOWN FROM BAR","block":"Supplemental Arrows-B","script":"Unknown","category":"Sm","kind":"glyph"},{"cp":10591,"name":"RIGHTWARDS HARPOON WITH BARB DOWN FROM BAR","block":"Supplemental Arrows-B","script":"Unknown","category":"Sm","kind":"glyph"},{"cp":10592,"name":"UPWARDS HARPOON WITH BARB LEFT FROM BAR","block":"Supplemental Arrows-B","script":"Unknown","category":"Sm","kind":"glyph"},{"cp":10593,"name":"DOWNWARDS HARPOON WITH BARB LEFT FROM BAR","block":"Supplemental Arrows-B","script":"Unknown","category":"Sm","kind":"glyph"},{"cp":10594,"name":"LEFTWARDS HARPOON WITH BARB UP ABOVE LEFTWARDS HARPOON WITH BARB DOWN","block":"Supplemental Arrows-B","script":"Unknown","category":"Sm","kind":"glyph"},{"cp":10595,"name":"UPWARDS HARPOON WITH BARB LEFT BESIDE UPWARDS HARPOON WITH BARB RIGHT","block":"Supplemental Arrows-B","script":"Unknown","category":"Sm","kind":"glyph"},{"cp":10596,"name":"RIGHTWARDS HARPOON WITH BARB UP ABOVE RIGHTWARDS HARPOON WITH BARB DOWN","block":"Supplemental Arrows-B","script":"Unknown","category":"Sm","kind":"glyph"},{"cp":10597,"name":"DOWNWARDS HARPOON WITH BARB LEFT BESIDE DOWNWARDS HARPOON WITH BARB RIGHT","block":"Supplemental Arrows-B","script":"Unknown","category":"Sm","kind":"glyph"},{"cp":10598,"name":"LEFTWARDS HARPOON WITH BARB UP ABOVE RIGHTWARDS HARPOON WITH BARB UP","block":"Supplemental Arrows-B","script":"Unknown","category":"Sm","kind":"glyph"},{"cp":10599,"name":"LEFTWARDS HARPOON WITH BARB DOWN ABOVE RIGHTWARDS HARPOON WITH BARB DOWN","block":"Supplemental Arrows-B","script":"Unknown","category":"Sm","kind":"glyph"},{"cp":10600,"name":"RIGHTWARDS HARPOON WITH BARB UP ABOVE LEFTWARDS HARPOON WITH BARB UP","block":"Supplemental Arrows-B","script":"Unknown","category":"Sm","kind":"glyph"},{"cp":10601,"name":"RIGHTWARDS HARPOON WITH BARB DOWN ABOVE LEFTWARDS HARPOON WITH BARB DOWN","block":"Supplemental Arrows-B","script":"Unknown","category":"Sm","kind":"glyph"},{"cp":10602,"name":"LEFTWARDS HARPOON WITH BARB UP ABOVE LONG DASH","block":"Supplemental Arrows-B","script":"Unknown","category":"Sm","kind":"glyph"},{"cp":10603,"name":"LEFTWARDS HARPOON WITH BARB DOWN BELOW LONG DASH","block":"Supplemental Arrows-B","script":"Unknown","category":"Sm","kind":"glyph"},{"cp":10604,"name":"RIGHTWARDS HARPOON WITH BARB UP ABOVE LONG DASH","block":"Supplemental Arrows-B","script":"Unknown","category":"Sm","kind":"glyph"},{"cp":10605,"name":"RIGHTWARDS HARPOON WITH BARB DOWN BELOW LONG DASH","block":"Supplemental Arrows-B","script":"Unknown","category":"Sm","kind":"glyph"},{"cp":10606,"name":"UPWARDS HARPOON WITH BARB LEFT BESIDE DOWNWARDS HARPOON WITH BARB RIGHT","block":"Supplemental Arrows-B","script":"Unknown","category":"Sm","kind":"glyph"},{"cp":10607,"name":"DOWNWARDS HARPOON WITH BARB LEFT BESIDE UPWARDS HARPOON WITH BARB RIGHT","block":"Supplemental Arrows-B","script":"Unknown","category":"Sm","kind":"glyph"},{"cp":10608,"name":"RIGHT DOUBLE ARROW WITH ROUNDED HEAD","block":"Supplemental Arrows-B","script":"Unknown","category":"Sm","kind":"glyph"},{"cp":10609,"name":"EQUALS SIGN ABOVE RIGHTWARDS ARROW","block":"Supplemental Arrows-B","script":"Unknown","category":"Sm","kind":"glyph"},{"cp":10610,"name":"TILDE OPERATOR ABOVE RIGHTWARDS ARROW","block":"Supplemental Arrows-B","script":"Unknown","category":"Sm","kind":"glyph"},{"cp":10611,"name":"LEFTWARDS ARROW ABOVE TILDE OPERATOR","block":"Supplemental Arrows-B","script":"Unknown","category":"Sm","kind":"glyph"},{"cp":10612,"name":"RIGHTWARDS ARROW ABOVE TILDE OPERATOR","block":"Supplemental Arrows-B","script":"Unknown","category":"Sm","kind":"glyph"},{"cp":10613,"name":"RIGHTWARDS ARROW ABOVE ALMOST EQUAL TO","block":"Supplemental Arrows-B","script":"Unknown","category":"Sm","kind":"glyph"},{"cp":10614,"name":"LESS-THAN ABOVE LEFTWARDS ARROW","block":"Supplemental Arrows-B","script":"Unknown","category":"Sm","kind":"glyph"},{"cp":10615,"name":"LEFTWARDS ARROW THROUGH LESS-THAN","block":"Supplemental Arrows-B","script":"Unknown","category":"Sm","kind":"glyph"},{"cp":10616,"name":"GREATER-THAN ABOVE RIGHTWARDS ARROW","block":"Supplemental Arrows-B","script":"Unknown","category":"Sm","kind":"glyph"},{"cp":10617,"name":"SUBSET ABOVE RIGHTWARDS ARROW","block":"Supplemental Arrows-B","script":"Unknown","category":"Sm","kind":"glyph"},{"cp":10618,"name":"LEFTWARDS ARROW THROUGH SUBSET","block":"Supplemental Arrows-B","script":"Unknown","category":"Sm","kind":"glyph"},{"cp":10619,"name":"SUPERSET ABOVE LEFTWARDS ARROW","block":"Supplemental Arrows-B","script":"Unknown","category":"Sm","kind":"glyph"},{"cp":10620,"name":"LEFT FISH TAIL","block":"Supplemental Arrows-B","script":"Unknown","category":"Sm","kind":"glyph"},{"cp":10621,"name":"RIGHT FISH TAIL","block":"Supplemental Arrows-B","script":"Unknown","category":"Sm","kind":"glyph"},{"cp":10622,"name":"UP FISH TAIL","block":"Supplemental Arrows-B","script":"Unknown","category":"Sm","kind":"glyph"},{"cp":10623,"name":"DOWN FISH TAIL","block":"Supplemental Arrows-B","script":"Unknown","category":"Sm","kind":"glyph"}]
