[{"cp":5120,"name":"CANADIAN SYLLABICS HYPHEN","block":"Unified Canadian Aboriginal Syllabics","script":"Unknown","category":"Pd","kind":"glyph","flags":["dash"],"keywords":["dash"],"featuredIn":["dashes"]},{"cp":5121,"name":"CANADIAN SYLLABICS E","block":"Unified Canadian Aboriginal Syllabics","script":"Unknown","category":"Lo","kind":"glyph"},{"cp":5122,"name":"CANADIAN SYLLABICS AAI","block":"Unified Canadian Aboriginal Syllabics","script":"Unknown","category":"Lo","kind":"glyph"},{"cp":5123,"name":"CANADIAN SYLLABICS I","block":"Unified Canadian Aboriginal Syllabics","script":"Unknown","category":"Lo","kind":"glyph"},{"cp":5124,"name":"CANADIAN SYLLABICS II","block":"Unified Canadian Aboriginal Syllabics","script":"Unknown","category":"Lo","kind":"glyph"},{"cp":5125,"name":"CANADIAN SYLLABICS O","block":"Unified Canadian Aboriginal Syllabics","script":"Unknown","category":"Lo","kind":"glyph"},{"cp":5126,"name":"CANADIAN SYLLABICS OO","block":"Unified Canadian Aboriginal Syllabics","script":"Unknown","category":"Lo","kind":"glyph"},{"cp":5127,"name":"CANADIAN SYLLABICS Y-CREE OO","block":"Unified Canadian Aboriginal Syllabics","script":"Unknown","category":"Lo","kind":"glyph"},{"cp":5128,"name":"CANADIAN SYLLABICS CARRIER EE","block":"Unified Canadian Aboriginal Syllabics","script":"Unknown","category":"Lo","kind":"glyph"},{"cp":5129,"name":"CANADIAN SYLLABICS CARRIER I","block":"Unified Canadian Aboriginal Syllabics","script":"Unknown","category":"Lo","kind":"glyph"},{"cp":5130,"name":"CANADIAN SYLLABICS A","block":"Unified Canadian Aboriginal Syllabics","script":"Unknown","category":"Lo","kind":"glyph"},{"cp":5131,"name":"CANADIAN SYLLABICS AA","block":"Unified Canadian Aboriginal Syllabics","script":"Unknown","category":"Lo","kind":"glyph"},{"cp":5132,"name":"CANADIAN SYLLABICS WE","block":"Unified Canadian Aboriginal Syllabics","script":"Unknown","category":"Lo","kind":"glyph"},{"cp":5133,"name":"CANADIAN SYLLABICS WEST-CREE WE","block":"Unified Canadian Aboriginal Syllabics","script":"Unknown","category":"Lo","kind":"glyph"},{"cp":5134,"name":"CANADIAN SYLLABICS WI","block":"Unified Canadian Aboriginal Syllabics","script":"Unknown","category":"Lo","kind":"glyph"},{"cp":5135,"name":"CANADIAN SYLLABICS WEST-CREE WI","block":"Unified Canadian Aboriginal Syllabics","script":"Unknown","category":"Lo","kind":"glyph"},{"cp":5136,"name":"CANADIAN SYLLABICS WII","block":"Unified Canadian Aboriginal Syllabics","script":"Unknown","category":"Lo","kind":"glyph"},{"cp":5137,"name":"CANADIAN SYLLABICS WEST-CREE WII","block":"Unified Canadian Aboriginal Syllabics","script":"Unknown","category":"Lo","kind":"glyph"},{"cp":5138,"name":"CANADIAN SYLLABICS WO","block":"Unified Canadian Aboriginal Syllabics","script":"Unknown","category":"Lo","kind":"glyph"},{"cp":5139,"name":"CANADIAN SYLLABICS WEST-CREE WO","block":"Unified Canadian Aboriginal Syllabics","script":"Unknown","category":"Lo","kind":"glyph"},{"cp":5140,"name":"CANADIAN SYLLABICS WOO","block":"Unified Canadian Aboriginal Syllabics","script":"Unknown","category":"Lo","kind":"glyph"},{"cp":5141,"name":"CANADIAN SYLLABICS WEST-CREE WOO","block":"Unified Canadian Aboriginal Syllabics","script":"Unknown","category":"Lo","kind":"glyph"},{"cp":5142,"name":"CANADIAN SYLLABICS NASKAPI WOO","block":"Unified Canadian Aboriginal Syllabics","script":"Unknown","category":"Lo","kind":"glyph"},{"cp":5143,"name":"CANADIAN SYLLABICS WA","block":"Unified Canadian Aboriginal Syllabics","script":"Unknown","category":"Lo","kind":"glyph"},{"cp":5144,"name":"CANADIAN SYLLABICS WEST-CREE WA","block":"Unified Canadian Aboriginal Syllabics","script":"Unknown","category":"Lo","kind":"glyph"},{"cp":5145,"name":"CANADIAN SYLLABICS WAA","block":"Unified Canadian Aboriginal Syllabics","script":"Unknown","category":"Lo","kind":"glyph"},{"cp":5146,"name":"CANADIAN SYLLABICS WEST-CREE WAA","block":"Unified Canadian Aboriginal Syllabics","script":"Unknown","category":"Lo","kind":"glyph"},{"cp":5147,"name":"CANADIAN SYLLABICS NASKAPI WAA","block":"Unified Canadian Aboriginal Syllabics","script":"Unknown","category":"Lo","kind":"glyph"},{"cp":5148,"name":"CANADIAN SYLLABICS AI","block":"Unified Canadian Aboriginal Syllabics","script":"Unknown","category":"Lo","kind":"glyph"},{"cp":5149,"name":"CANADIAN SYLLABICS Y-CREE W","block":"Unified Canadian Aboriginal Syllabics","script":"Unknown","category":"Lo","kind":"glyph"},{"cp":5150,"name":"CANADIAN SYLLABICS GLOTTAL STOP","block":"Unified Canadian Aboriginal Syllabics","script":"Unknown","category":"Lo","kind":"glyph"},{"cp":5151,"name":"CANADIAN SYLLABICS FINAL ACUTE","block":"Unified Canadian Aboriginal Syllabics","script":"Unknown","category":"Lo","kind":"glyph"},{"cp":5152,"name":"CANADIAN SYLLABICS FINAL GRAVE","block":"Unified Canadian Aboriginal Syllabics","script":"Unknown","category":"Lo","kind":"glyph"},{"cp":5153,"name":"CANADIAN SYLLABICS FINAL BOTTOM HALF RING","block":"Unified Canadian Aboriginal Syllabics","script":"Unknown","category":"Lo","kind":"glyph"},{"cp":5154,"name":"CANADIAN SYLLABICS FINAL TOP HALF RING","block":"Unified Canadian Aboriginal Syllabics","script":"Unknown","category":"Lo","kind":"glyph"},{"cp":5155,"name":"CANADIAN SYLLABICS FINAL RIGHT HALF RING","block":"Unified Canadian Aboriginal Syllabics","script":"Unknown","category":"Lo","kind":"glyph"},{"cp":5156,"name":"CANADIAN SYLLABICS FINAL RING","block":"Unified Canadian Aboriginal Syllabics","script":"Unknown","category":"Lo","kind":"glyph"},{"cp":5157,"name":"CANADIAN SYLLABICS FINAL DOUBLE ACUTE","block":"Unified Canadian Aboriginal Syllabics","script":"Unknown","category":"Lo","kind":"glyph"},{"cp":5158,"name":"CANADIAN SYLLABICS FINAL DOUBLE SHORT VERTICAL STROKES","block":"Unified Canadian Aboriginal Syllabics","script":"Unknown","category":"Lo","kind":"glyph"},{"cp":5159,"name":"CANADIAN SYLLABICS FINAL MIDDLE DOT","block":"Unified Canadian Aboriginal Syllabics","script":"Unknown","category":"Lo","kind":"glyph"},{"cp":5160,"name":"CANADIAN SYLLABICS FINAL SHORT HORIZONTAL STROKE","block":"Unified Canadian Aboriginal Syllabics","script":"Unknown","category":"Lo","kind":"glyph"},{"cp":5161,"name":"CANADIAN SYLLABICS FINAL PLUS","block":"Unified Canadian Aboriginal Syllabics","script":"Unknown","category":"Lo","kind":"glyph"},{"cp":5162,"name":"CANADIAN SYLLABICS FINAL DOWN TACK","block":"Unified Canadian Aboriginal Syllabics","script":"Unknown","category":"Lo","kind":"glyph"},{"cp":5163,"name":"CANADIAN SYLLABICS EN","block":"Unified Canadian Aboriginal Syllabics","script":"Unknown","category":"Lo","kind":"glyph"},{"cp":5164,"name":"CANADIAN SYLLABICS IN","block":"Unified Canadian Aboriginal Syllabics","script":"Unknown","category":"Lo","kind":"glyph"},{"cp":5165,"name":"CANADIAN SYLLABICS ON","block":"Unified Canadian Aboriginal Syllabics","script":"Unknown","category":"Lo","kind":"glyph"},{"cp":5166,"name":"CANADIAN SYLLABICS AN","block":"Unified Canadian Aboriginal Syllabics","script":"Unknown","category":"Lo","kind":"glyph"},{"cp":5167,"name":"CANADIAN SYLLABICS PE","block":"Unified Canadian Aboriginal Syllabics","script":"Unknown","category":"Lo","kind":"glyph"},{"cp":5168,"name":"CANADIAN SYLLABICS PAAI","block":"Unified Canadian Aboriginal Syllabics","script":"Unknown","category":"Lo","kind":"glyph"},{"cp":5169,"name":"CANADIAN SYLLABICS PI","block":"Unified Canadian Aboriginal Syllabics","script":"Unknown","category":"Lo","kind":"glyph"},{"cp":5170,"name":"CANADIAN SYLLABICS PII","block":"Unified Canadian Aboriginal Syllabics","script":"Unknown","category":"Lo","kind":"glyph"},{"cp":5171,"name":"CANADIAN SYLLABICS PO","block":"Unified Canadian Aboriginal Syllabics","script":"Unknown","category":"Lo","kind":"glyph"},{"cp":5172,"name":"CANADIAN SYLLABICS POO","block":"Unified Canadian Aboriginal Syllabics","script":"Unknown","category":"Lo","kind":"glyph"},{"cp":5173,"name":"CANADIAN SYLLABICS Y-CREE POO","block":"Unified Canadian Aboriginal Syllabics","script":"Unknown","category":"Lo","kind":"glyph"},{"cp":5174,"name":"CANADIAN SYLLABICS CARRIER HEE","block":"Unified Canadian Aboriginal Syllabics","script":"Unknown","category":"Lo","kind":"glyph"},{"cp":5175,"name":"CANADIAN SYLLABICS CARRIER HI","block":"Unified Canadian Aboriginal Syllabics","script":"Unknown","category":"Lo","kind":"glyph"},{"cp":5176,"name":"CANADIAN SYLLABICS PA","block":"Unified Canadian Aboriginal Syllabics","script":"Unknown","category":"Lo","kind":"glyph"},{"cp":5177,"name":"CANADIAN SYLLABICS PAA","block":"Unified Canadian Aboriginal Syllabics","script":"Unknown","category":"Lo","kind":"glyph"},{"cp":5178,"name":"CANADIAN SYLLABICS PWE","block":"Unified Canadian Aboriginal Syllabics","script":"Unknown","category":"Lo","kind":"glyph"},{"cp":5179,"name":"CANADIAN SYLLABICS WEST-CREE PWE","block":"Unified Canadian Aboriginal Syllabics","script":"Unknown","category":"Lo","kind":"glyph"},{"cp":5180,"name":"CANADIAN SYLLABICS PWI","block":"Unified Canadian Aboriginal Syllabics","script":"Unknown","category":"Lo","kind":"glyph"},{"cp":5181,"name":"CANADIAN SYLLABICS WEST-CREE PWI","block":"Unified Canadian Aboriginal Syllabics","script":"Unknown","category":"Lo","kind":"glyph"},{"cp":5182,"name":"CANADIAN SYLLABICS PWII","block":"Unified Canadian Aboriginal Syllabics","script":"Unknown","category":"Lo","kind":"glyph"},{"cp":5183,"name":"CANADIAN SYLLABICS WEST-CREE PWII","block":"Unified Canadian Aboriginal Syllabics","script":"Unknown","category":"Lo","kind":"glyph"},{"cp":5184,"name":"CANADIAN SYLLABICS PWO","block":"Unified Canadian Aboriginal Syllabics","script":"Unknown","category":"Lo","kind":"glyph"},{"cp":5185,"name":"CANADIAN SYLLABICS WEST-CREE PWO","block":"Unified Canadian Aboriginal Syllabics","script":"Unknown","category":"Lo","kind":"glyph"},{"cp":5186,"name":"CANADIAN SYLLABICS PWOO","block":"Unified Canadian Aboriginal Syllabics","script":"Unknown","category":"Lo","kind":"glyph"},{"cp":5187,"name":"CANADIAN SYLLABICS WEST-CREE PWOO","block":"Unified Canadian Aboriginal Syllabics","script":"Unknown","category":"Lo","kind":"glyph"},{"cp":5188,"name":"CANADIAN SYLLABICS PWA","block":"Unified Canadian Aboriginal Syllabics","script":"Unknown","category":"Lo","kind":"glyph"},{"cp":5189,"name":"CANADIAN SYLLABICS WEST-CREE PWA","block":"Unified Canadian Aboriginal Syllabics","script":"Unknown","category":"Lo","kind":"glyph"},{"cp":5190,"name":"CANADIAN SYLLABICS PWAA","block":"Unified Canadian Aboriginal Syllabics","script":"Unknown","category":"Lo","kind":"glyph"},{"cp":5191,"name":"CANADIAN SYLLABICS WEST-CREE PWAA","block":"Unified Canadian Aboriginal Syllabics","script":"Unknown","category":"Lo","kind":"glyph"},{"cp":5192,"name":"CANADIAN SYLLABICS Y-CREE PWAA","block":"Unified Canadian Aboriginal Syllabics","script":"Unknown","category":"Lo","kind":"glyph"},{"cp":5193,"name":"CANADIAN SYLLABICS P","block":"Unified Canadian Aboriginal Syllabics","script":"Unknown","category":"Lo","kind":"glyph"},{"cp":5194,"name":"CANADIAN SYLLABICS WEST-CREE P","block":"Unified Canadian Aboriginal Syllabics","script":"Unknown","category":"Lo","kind":"glyph"},{"cp":5195,"name":"CANADIAN SYLLABICS CARRIER H","block":"Unified Canadian Aboriginal Syllabics","script":"Unknown","category":"Lo","kind":"glyph"},{"cp":5196,"name":"CANADIAN SYLLABICS TE","block":"Unified Canadian Aboriginal Syllabics","script":"Unknown","category":"Lo","kind":"glyph"},{"cp":5197,"name":"CANADIAN SYLLABICS TAAI","block":"Unified Canadian Aboriginal Syllabics","script":"Unknown","category":"Lo","kind":"glyph"},{"cp":5198,"name":"CANADIAN SYLLABICS TI","block":"Unified Canadian Aboriginal Syllabics","script":"Unknown","category":"Lo","kind":"glyph"},{"cp":5199,"name":"CANADIAN SYLLABICS TII","block":"Unified Canadian Aboriginal Syllabics","script":"Unknown","category":"Lo","kind":"glyph"},{"cp":5200,"name":"CANADIAN SYLLABICS TO","block":"Unified Canadian Aboriginal Syllabics","script":"Unknown","category":"Lo","kind":"glyph"},{"cp":5201,"name":"CANADIAN SYLLABICS TOO","block":"Unified Canadian Aboriginal Syllabics","script":"Unknown","category":"Lo","kind":"glyph"},{"cp":5202,"name":"CANADIAN SYLLABICS Y-CREE TOO","block":"Unified Canadian Aboriginal Syllabics","script":"Unknown","category":"Lo","kind":"glyph"},{"cp":5203,"name":"CANADIAN SYLLABICS CARRIER DEE","block":"Unified Canadian Aboriginal Syllabics","script":"Unknown","category":"Lo","kind":"glyph"},{"cp":5204,"name":"CANADIAN SYLLABICS CARRIER DI","block":"Unified Canadian Aboriginal Syllabics","script":"Unknown","category":"Lo","kind":"glyph"},{"cp":5205,"name":"CANADIAN SYLLABICS TA","block":"Unified Canadian Aboriginal Syllabics","script":"Unknown","category":"Lo","kind":"glyph"},{"cp":5206,"name":"CANADIAN SYLLABICS TAA","block":"Unified Canadian Aboriginal Syllabics","script":"Unknown","category":"Lo","kind":"glyph"},{"cp":5207,"name":"CANADIAN SYLLABICS TWE","block":"Unified Canadian Aboriginal Syllabics","script":"Unknown","category":"Lo","kind":"glyph"},{"cp":5208,"name":"CANADIAN SYLLABICS WEST-CREE TWE","block":"Unified Canadian Aboriginal Syllabics","script":"Unknown","category":"Lo","kind":"glyph"},{"cp":5209,"name":"CANADIAN SYLLABICS TWI","block":"Unified Canadian Aboriginal Syllabics","script":"Unknown","category":"Lo","kind":"glyph"},{"cp":5210,"name":"CANADIAN SYLLABICS WEST-CREE TWI","block":"Unified Canadian Aboriginal Syllabics","script":"Unknown","category":"Lo","kind":"glyph"},{"cp":5211,"name":"CANADIAN SYLLABICS TWII","block":"Unified Canadian Aboriginal Syllabics","script":"Unknown","category":"Lo","kind":"glyph"},{"cp":5212,"name":"CANADIAN SYLLABICS WEST-CREE TWII","block":"Unified Canadian Aboriginal Syllabics","script":"Unknown","category":"Lo","kind":"glyph"},{"cp":5213,"name":"CANADIAN SYLLABICS TWO","block":"Unified Canadian Aboriginal Syllabics","script":"Unknown","category":"Lo","kind":"glyph"},{"cp":5214,"name":"CANADIAN SYLLABICS WEST-CREE TWO","block":"Unified Canadian Aboriginal Syllabics","script":"Unknown","category":"Lo","kind":"glyph"},{"cp":5215,"name":"CANADIAN SYLLABICS TWOO","block":"Unified Canadian Aboriginal Syllabics","script":"Unknown","category":"Lo","kind":"glyph"},{"cp":5216,"name":"CANADIAN SYLLABICS WEST-CREE TWOO","block":"Unified Canadian Aboriginal Syllabics","script":"Unknown","category":"Lo","kind":"glyph"},{"cp":5217,"name":"CANADIAN SYLLABICS TWA","block":"Unified Canadian Aboriginal Syllabics","script":"Unknown","category":"Lo","kind":"glyph"},{"cp":5218,"name":"CANADIAN SYLLABICS WEST-CREE TWA","block":"Unified Canadian Aboriginal Syllabics","script":"Unknown","category":"Lo","kind":"glyph"},{"cp":5219,"name":"CANADIAN SYLLABICS TWAA","block":"Unified Canadian Aboriginal Syllabics","script":"Unknown","category":"Lo","kind":"glyph"},{"cp":5220,"name":"CANADIAN SYLLABICS WEST-CREE TWAA","block":"Unified Canadian Aboriginal Syllabics","script":"Unknown","category":"Lo","kind":"glyph"},{"cp":5221,"name":"CANADIAN SYLLABICS NASKAPI TWAA","block":"Unified Canadian Aboriginal Syllabics","script":"Unknown","category":"Lo","kind":"glyph"},{"cp":5222,"name":"CANADIAN SYLLABICS T","block":"Unified Canadian Aboriginal Syllabics","script":"Unknown","category":"Lo","kind":"glyph"},{"cp":5223,"name":"CANADIAN SYLLABICS TTE","block":"Unified Canadian Aboriginal Syllabics","script":"Unknown","category":"Lo","kind":"glyph"},{"cp":5224,"name":"CANADIAN SYLLABICS TTI","block":"Unified Canadian Aboriginal Syllabics","script":"Unknown","category":"Lo","kind":"glyph"},{"cp":5225,"name":"CANADIAN SYLLABICS TTO","block":"Unified Canadian Aboriginal Syllabics","script":"Unknown","category":"Lo","kind":"glyph"},{"cp":5226,"name":"CANADIAN SYLLABICS TTA","block":"Unified Canadian Aboriginal Syllabics","script":"Unknown","category":"Lo","kind":"glyph"},{"cp":5227,"name":"CANADIAN SYLLABICS KE","block":"Unified Canadian Aboriginal Syllabics","script":"Unknown","category":"Lo","kind":"glyph"},{"cp":5228,"name":"CANADIAN SYLLABICS KAAI","block":"Unified Canadian Aboriginal Syllabics","script":"Unknown","category":"Lo","kind":"glyph"},{"cp":5229,"name":"CANADIAN SYLLABICS KI","block":"Unified Canadian Aboriginal Syllabics","script":"Unknown","category":"Lo","kind":"glyph"},{"cp":5230,"name":"CANADIAN SYLLABICS KII","block":"Unified Canadian Aboriginal Syllabics","script":"Unknown","category":"Lo","kind":"glyph"},{"cp":5231,"name":"CANADIAN SYLLABICS KO","block":"Unified Canadian Aboriginal Syllabics","script":"Unknown","category":"Lo","kind":"glyph"},{"cp":5232,"name":"CANADIAN SYLLABICS KOO","block":"Unified Canadian Aboriginal Syllabics","script":"Unknown","category":"Lo","kind":"glyph"},{"cp":5233,"name":"CANADIAN SYLLABICS Y-CREE KOO","block":"Unified Canadian Aboriginal Syllabics","script":"Unknown","category":"Lo","kind":"glyph"},{"cp":5234,"name":"CANADIAN SYLLABICS KA","block":"Unified Canadian Aboriginal Syllabics","script":"Unknown","category":"Lo","kind":"glyph"},{"cp":5235,"name":"CANADIAN SYLLABICS KAA","block":"Unified Canadian Aboriginal Syllabics","script":"Unknown","category":"Lo","kind":"glyph"},{"cp":5236,"name":"CANADIAN SYLLABICS KWE","block":"Unified Canadian Aboriginal Syllabics","script":"Unknown","category":"Lo","kind":"glyph"},{"cp":5237,"name":"CANADIAN SYLLABICS WEST-CREE KWE","block":"Unified Canadian Aboriginal Syllabics","script":"Unknown","category":"Lo","kind":"glyph"},{"cp":5238,"name":"CANADIAN SYLLABICS KWI","block":"Unified Canadian Aboriginal Syllabics","script":"Unknown","category":"Lo","kind":"glyph"},{"cp":5239,"name":"CANADIAN SYLLABICS WEST-CREE KWI","block":"Unified Canadian Aboriginal Syllabics","script":"Unknown","category":"Lo","kind":"glyph"},{"cp":5240,"name":"CANADIAN SYLLABICS KWII","block":"Unified Canadian Aboriginal Syllabics","script":"Unknown","category":"Lo","kind":"glyph"},{"cp":5241,"name":"CANADIAN SYLLABICS WEST-CREE KWII","block":"Unified Canadian Aboriginal Syllabics","script":"Unknown","category":"Lo","kind":"glyph"},{"cp":5242,"name":"CANADIAN SYLLABICS KWO","block":"Unified Canadian Aboriginal Syllabics","script":"Unknown","category":"Lo","kind":"glyph"},{"cp":5243,"name":"CANADIAN SYLLABICS WEST-CREE KWO","block":"Unified Canadian Aboriginal Syllabics","script":"Unknown","category":"Lo","kind":"glyph"},{"cp":5244,"name":"CANADIAN SYLLABICS KWOO","block":"Unified Canadian Aboriginal Syllabics","script":"Unknown","category":"Lo","kind":"glyph"},{"cp":5245,"name":"CANADIAN SYLLABICS WEST-CREE KWOO","block":"Unified Canadian Aboriginal Syllabics","script":"Unknown","category":"Lo","kind":"glyph"},{"cp":5246,"name":"CANADIAN SYLLABICS KWA","block":"Unified Canadian Aboriginal Syllabics","script":"Unknown","category":"Lo","kind":"glyph"},{"cp":5247,"name":"CANADIAN SYLLABICS WEST-CREE KWA","block":"Unified Canadian Aboriginal Syllabics","script":"Unknown","category":"Lo","kind":"glyph"},{"cp":5248,"name":"CANADIAN SYLLABICS KWAA","block":"Unified Canadian Aboriginal Syllabics","script":"Unknown","category":"Lo","kind":"glyph"},{"cp":5249,"name":"CANADIAN SYLLABICS WEST-CREE KWAA","block":"Unified Canadian Aboriginal Syllabics","script":"Unknown","category":"Lo","kind":"glyph"},{"cp":5250,"name":"CANADIAN SYLLABICS NASKAPI KWAA","block":"Unified Canadian Aboriginal Syllabics","script":"Unknown","category":"Lo","kind":"glyph"},{"cp":5251,"name":"CANADIAN SYLLABICS K","block":"Unified Canadian Aboriginal Syllabics","script":"Unknown","category":"Lo","kind":"glyph"},{"cp":5252,"name":"CANADIAN SYLLABICS KW","block":"Unified Canadian Aboriginal Syllabics","script":"Unknown","category":"Lo","kind":"glyph"},{"cp":5253,"name":"CANADIAN SYLLABICS SOUTH-SLAVEY KEH","block":"Unified Canadian Aboriginal Syllabics","script":"Unknown","category":"Lo","kind":"glyph"},{"cp":5254,"name":"CANADIAN SYLLABICS SOUTH-SLAVEY KIH","block":"Unified Canadian Aboriginal Syllabics","script":"Unknown","category":"Lo","kind":"glyph"},{"cp":5255,"name":"CANADIAN SYLLABICS SOUTH-SLAVEY KOH","block":"Unified Canadian Aboriginal Syllabics","script":"Unknown","category":"Lo","kind":"glyph"},{"cp":5256,"name":"CANADIAN SYLLABICS SOUTH-SLAVEY KAH","block":"Unified Canadian Aboriginal Syllabics","script":"Unknown","category":"Lo","kind":"glyph"},{"cp":5257,"name":"CANADIAN SYLLABICS CE","block":"Unified Canadian Aboriginal Syllabics","script":"Unknown","category":"Lo","kind":"glyph"},{"cp":5258,"name":"CANADIAN SYLLABICS CAAI","block":"Unified Canadian Aboriginal Syllabics","script":"Unknown","category":"Lo","kind":"glyph"},{"cp":5259,"name":"CANADIAN SYLLABICS CI","block":"Unified Canadian Aboriginal Syllabics","script":"Unknown","category":"Lo","kind":"glyph"},{"cp":5260,"name":"CANADIAN SYLLABICS CII","block":"Unified Canadian Aboriginal Syllabics","script":"Unknown","category":"Lo","kind":"glyph"},{"cp":5261,"name":"CANADIAN SYLLABICS CO","block":"Unified Canadian Aboriginal Syllabics","script":"Unknown","category":"Lo","kind":"glyph"},{"cp":5262,"name":"CANADIAN SYLLABICS COO","block":"Unified Canadian Aboriginal Syllabics","script":"Unknown","category":"Lo","kind":"glyph"},{"cp":5263,"name":"CANADIAN SYLLABICS Y-CREE COO","block":"Unified Canadian Aboriginal Syllabics","script":"Unknown","category":"Lo","kind":"glyph"},{"cp":5264,"name":"CANADIAN SYLLABICS CA","block":"Unified Canadian Aboriginal Syllabics","script":"Unknown","category":"Lo","kind":"glyph"},{"cp":5265,"name":"CANADIAN SYLLABICS CAA","block":"Unified Canadian Aboriginal Syllabics","script":"Unknown","category":"Lo","kind":"glyph"},{"cp":5266,"name":"CANADIAN SYLLABICS CWE","block":"Unified Canadian Aboriginal Syllabics","script":"Unknown","category":"Lo","kind":"glyph"},{"cp":5267,"name":"CANADIAN SYLLABICS WEST-CREE CWE","block":"Unified Canadian Aboriginal Syllabics","script":"Unknown","category":"Lo","kind":"glyph"},{"cp":5268,"name":"CANADIAN SYLLABICS CWI","block":"Unified Canadian Aboriginal Syllabics","script":"Unknown","category":"Lo","kind":"glyph"},{"cp":5269,"name":"CANADIAN SYLLABICS WEST-CREE CWI","block":"Unified Canadian Aboriginal Syllabics","script":"Unknown","category":"Lo","kind":"glyph"},{"cp":5270,"name":"CANADIAN SYLLABICS CWII","block":"Unified Canadian Aboriginal Syllabics","script":"Unknown","category":"Lo","kind":"glyph"},{"cp":5271,"name":"CANADIAN SYLLABICS WEST-CREE CWII","block":"Unified Canadian Aboriginal Syllabics","script":"Unknown","category":"Lo","kind":"glyph"},{"cp":5272,"name":"CANADIAN SYLLABICS CWO","block":"Unified Canadian Aboriginal Syllabics","script":"Unknown","category":"Lo","kind":"glyph"},{"cp":5273,"name":"CANADIAN SYLLABICS WEST-CREE CWO","block":"Unified Canadian Aboriginal Syllabics","script":"Unknown","category":"Lo","kind":"glyph"},{"cp":5274,"name":"CANADIAN SYLLABICS CWOO","block":"Unified Canadian Aboriginal Syllabics","script":"Unknown","category":"Lo","kind":"glyph"},{"cp":5275,"name":"CANADIAN SYLLABICS WEST-CREE CWOO","block":"Unified Canadian Aboriginal Syllabics","script":"Unknown","category":"Lo","kind":"glyph"},{"cp":5276,"name":"CANADIAN SYLLABICS CWA","block":"Unified Canadian Aboriginal Syllabics","script":"Unknown","category":"Lo","kind":"glyph"},{"cp":5277,"name":"CANADIAN SYLLABICS WEST-CREE CWA","block":"Unified Canadian Aboriginal Syllabics","script":"Unknown","category":"Lo","kind":"glyph"},{"cp":5278,"name":"CANADIAN SYLLABICS CWAA","block":"Unified Canadian Aboriginal Syllabics","script":"Unknown","category":"Lo","kind":"glyph"},{"cp":5279,"name":"CANADIAN SYLLABICS WEST-CREE CWAA","block":"Unified Canadian Aboriginal Syllabics","script":"Unknown","category":"Lo","kind":"glyph"},{"cp":5280,"name":"CANADIAN SYLLABICS NASKAPI CWAA","block":"Unified Canadian Aboriginal Syllabics","script":"Unknown","category":"Lo","kind":"glyph"},{"cp":5281,"name":"CANADIAN SYLLABICS C","block":"Unified Canadian Aboriginal Syllabics","script":"Unknown","category":"Lo","kind":"glyph"},{"cp":5282,"name":"CANADIAN SYLLABICS SAYISI TH","block":"Unified Canadian Aboriginal Syllabics","script":"Unknown","category":"Lo","kind":"glyph"},{"cp":5283,"name":"CANADIAN SYLLABICS ME","block":"Unified Canadian Aboriginal Syllabics","script":"Unknown","category":"Lo","kind":"glyph"},{"cp":5284,"name":"CANADIAN SYLLABICS MAAI","block":"Unified Canadian Aboriginal Syllabics","script":"Unknown","category":"Lo","kind":"glyph"},{"cp":5285,"name":"CANADIAN SYLLABICS MI","block":"Unified Canadian Aboriginal Syllabics","script":"Unknown","category":"Lo","kind":"glyph"},{"cp":5286,"name":"CANADIAN SYLLABICS MII","block":"Unified Canadian Aboriginal Syllabics","script":"Unknown","category":"Lo","kind":"glyph"},{"cp":5287,"name":"CANADIAN SYLLABICS MO","block":"Unified Canadian Aboriginal Syllabics","script":"Unknown","category":"Lo","kind":"glyph"},{"cp":5288,"name":"CANADIAN SYLLABICS MOO","block":"Unified Canadian Aboriginal Syllabics","script":"Unknown","category":"Lo","kind":"glyph"},{"cp":5289,"name":"CANADIAN SYLLABICS Y-CREE MOO","block":"Unified Canadian Aboriginal Syllabics","script":"Unknown","category":"Lo","kind":"glyph"},{"cp":5290,"name":"CANADIAN SYLLABICS MA","block":"Unified Canadian Aboriginal Syllabics","script":"Unknown","category":"Lo","kind":"glyph"},{"cp":5291,"name":"CANADIAN SYLLABICS MAA","block":"Unified Canadian Aboriginal Syllabics","script":"Unknown","category":"Lo","kind":"glyph"},{"cp":5292,"name":"CANADIAN SYLLABICS MWE","block":"Unified Canadian Aboriginal Syllabics","script":"Unknown","category":"Lo","kind":"glyph"},{"cp":5293,"name":"CANADIAN SYLLABICS WEST-CREE MWE","block":"Unified Canadian Aboriginal Syllabics","script":"Unknown","category":"Lo","kind":"glyph"},{"cp":5294,"name":"CANADIAN SYLLABICS MWI","block":"Unified Canadian Aboriginal Syllabics","script":"Unknown","category":"Lo","kind":"glyph"},{"cp":5295,"name":"CANADIAN SYLLABICS WEST-CREE MWI","block":"Unified Canadian Aboriginal Syllabics","script":"Unknown","category":"Lo","kind":"glyph"},{"cp":5296,"name":"CANADIAN SYLLABICS MWII","block":"Unified Canadian Aboriginal Syllabics","script":"Unknown","category":"Lo","kind":"glyph"},{"cp":5297,"name":"CANADIAN SYLLABICS WEST-CREE MWII","block":"Unified Canadian Aboriginal Syllabics","script":"Unknown","category":"Lo","kind":"glyph"},{"cp":5298,"name":"CANADIAN SYLLABICS MWO","block":"Unified Canadian Aboriginal Syllabics","script":"Unknown","category":"Lo","kind":"glyph"},{"cp":5299,"name":"CANADIAN SYLLABICS WEST-CREE MWO","block":"Unified Canadian Aboriginal Syllabics","script":"Unknown","category":"Lo","kind":"glyph"},{"cp":5300,"name":"CANADIAN SYLLABICS MWOO","block":"Unified Canadian Aboriginal Syllabics","script":"Unknown","category":"Lo","kind":"glyph"},{"cp":5301,"name":"CANADIAN SYLLABICS WEST-CREE MWOO","block":"Unified Canadian Aboriginal Syllabics","script":"Unknown","category":"Lo","kind":"glyph"},{"cp":5302,"name":"CANADIAN SYLLABICS MWA","block":"Unified Canadian Aboriginal Syllabics","script":"Unknown","category":"Lo","kind":"glyph"},{"cp":5303,"name":"CANADIAN SYLLABICS WEST-CREE MWA","block":"Unified Canadian Aboriginal Syllabics","script":"Unknown","category":"Lo","kind":"glyph"},{"cp":5304,"name":"CANADIAN SYLLABICS MWAA","block":"Unified Canadian Aboriginal Syllabics","script":"Unknown","category":"Lo","kind":"glyph"},{"cp":5305,"name":"CANADIAN SYLLABICS WEST-CREE MWAA","block":"Unified Canadian Aboriginal Syllabics","script":"Unknown","category":"Lo","kind":"glyph"},{"cp":5306,"name":"CANADIAN SYLLABICS NASKAPI MWAA","block":"Unified Canadian Aboriginal Syllabics","script":"Unknown","category":"Lo","kind":"glyph"},{"cp":5307,"name":"CANADIAN SYLLABICS M","block":"Unified Canadian Aboriginal Syllabics","script":"Unknown","category":"Lo","kind":"glyph"},{"cp":5308,"name":"CANADIAN SYLLABICS WEST-CREE M","block":"Unified Canadian Aboriginal Syllabics","script":"Unknown","category":"Lo","kind":"glyph"},{"cp":5309,"name":"CANADIAN SYLLABICS MH","block":"Unified Canadian Aboriginal Syllabics","script":"Unknown","category":"Lo","kind":"glyph"},{"cp":5310,"name":"CANADIAN SYLLABICS ATHAPASCAN M","block":"Unified Canadian Aboriginal Syllabics","script":"Unknown","category":"Lo","kind":"glyph"},{"cp":5311,"name":"CANADIAN SYLLABICS SAYISI M","block":"Unified Canadian Aboriginal Syllabics","script":"Unknown","category":"Lo","kind":"glyph"},{"cp":5312,"name":"CANADIAN SYLLABICS NE","block":"Unified Canadian Aboriginal Syllabics","script":"Unknown","category":"Lo","kind":"glyph"},{"cp":5313,"name":"CANADIAN SYLLABICS NAAI","block":"Unified Canadian Aboriginal Syllabics","script":"Unknown","category":"Lo","kind":"glyph"},{"cp":5314,"name":"CANADIAN SYLLABICS NI","block":"Unified Canadian Aboriginal Syllabics","script":"Unknown","category":"Lo","kind":"glyph"},{"cp":5315,"name":"CANADIAN SYLLABICS NII","block":"Unified Canadian Aboriginal Syllabics","script":"Unknown","category":"Lo","kind":"glyph"},{"cp":5316,"name":"CANADIAN SYLLABICS NO","block":"Unified Canadian Aboriginal Syllabics","script":"Unknown","category":"Lo","kind":"glyph"},{"cp":5317,"name":"CANADIAN SYLLABICS NOO","block":"Unified Canadian Aboriginal Syllabics","script":"Unknown","category":"Lo","kind":"glyph"},{"cp":5318,"name":"CANADIAN SYLLABICS Y-CREE NOO","block":"Unified Canadian Aboriginal Syllabics","script":"Unknown","category":"Lo","kind":"glyph"},{"cp":5319,"name":"CANADIAN SYLLABICS NA","block":"Unified Canadian Aboriginal Syllabics","script":"Unknown","category":"Lo","kind":"glyph"},{"cp":5320,"name":"CANADIAN SYLLABICS NAA","block":"Unified Canadian Aboriginal Syllabics","script":"Unknown","category":"Lo","kind":"glyph"},{"cp":5321,"name":"CANADIAN SYLLABICS NWE","block":"Unified Canadian Aboriginal Syllabics","script":"Unknown","category":"Lo","kind":"glyph"},{"cp":5322,"name":"CANADIAN SYLLABICS WEST-CREE NWE","block":"Unified Canadian Aboriginal Syllabics","script":"Unknown","category":"Lo","kind":"glyph"},{"cp":5323,"name":"CANADIAN SYLLABICS NWA","block":"Unified Canadian Aboriginal Syllabics","script":"Unknown","category":"Lo","kind":"glyph"},{"cp":5324,"name":"CANADIAN SYLLABICS WEST-CREE NWA","block":"Unified Canadian Aboriginal Syllabics","script":"Unknown","category":"Lo","kind":"glyph"},{"cp":5325,"name":"CANADIAN SYLLABICS NWAA","block":"Unified Canadian Aboriginal Syllabics","script":"Unknown","category":"Lo","kind":"glyph"},{"cp":5326,"name":"CANADIAN SYLLABICS WEST-CREE NWAA","block":"Unified Canadian Aboriginal Syllabics","script":"Unknown","category":"Lo","kind":"glyph"},{"cp":5327,"name":"CANADIAN SYLLABICS NASKAPI NWAA","block":"Unified Canadian Aboriginal Syllabics","script":"Unknown","category":"Lo","kind":"glyph"},{"cp":5328,"name":"CANADIAN SYLLABICS N","block":"Unified Canadian Aboriginal Syllabics","script":"Unknown","category":"Lo","kind":"glyph"},{"cp":5329,"name":"CANADIAN SYLLABICS CARRIER NG","block":"Unified Canadian Aboriginal Syllabics","script":"Unknown","category":"Lo","kind":"glyph"},{"cp":5330,"name":"CANADIAN SYLLABICS NH","block":"Unified Canadian Aboriginal Syllabics","script":"Unknown","category":"Lo","kind":"glyph"},{"cp":5331,"name":"CANADIAN SYLLABICS LE","block":"Unified Canadian Aboriginal Syllabics","script":"Unknown","category":"Lo","kind":"glyph"},{"cp":5332,"name":"CANADIAN SYLLABICS LAAI","block":"Unified Canadian Aboriginal Syllabics","script":"Unknown","category":"Lo","kind":"glyph"},{"cp":5333,"name":"CANADIAN SYLLABICS LI","block":"Unified Canadian Aboriginal Syllabics","script":"Unknown","category":"Lo","kind":"glyph"},{"cp":5334,"name":"CANADIAN SYLLABICS LII","block":"Unified Canadian Aboriginal Syllabics","script":"Unknown","category":"Lo","kind":"glyph"},{"cp":5335,"name":"CANADIAN SYLLABICS LO","block":"Unified Canadian Aboriginal Syllabics","script":"Unknown","category":"Lo","kind":"glyph"},{"cp":5336,"name":"CANADIAN SYLLABICS LOO","block":"Unified Canadian Aboriginal Syllabics","script":"Unknown","category":"Lo","kind":"glyph"},{"cp":5337,"name":"CANADIAN SYLLABICS Y-CREE LOO","block":"Unified Canadian Aboriginal Syllabics","script":"Unknown","category":"Lo","kind":"glyph"},{"cp":5338,"name":"CANADIAN SYLLABICS LA","block":"Unified Canadian Aboriginal Syllabics","script":"Unknown","category":"Lo","kind":"glyph"},{"cp":5339,"name":"CANADIAN SYLLABICS LAA","block":"Unified Canadian Aboriginal Syllabics","script":"Unknown","category":"Lo","kind":"glyph"},{"cp":5340,"name":"CANADIAN SYLLABICS LWE","block":"Unified Canadian Aboriginal Syllabics","script":"Unknown","category":"Lo","kind":"glyph"},{"cp":5341,"name":"CANADIAN SYLLABICS WEST-CREE LWE","block":"Unified Canadian Aboriginal Syllabics","script":"Unknown","category":"Lo","kind":"glyph"},{"cp":5342,"name":"CANADIAN SYLLABICS LWI","block":"Unified Canadian Aboriginal Syllabics","script":"Unknown","category":"Lo","kind":"glyph"},{"cp":5343,"name":"CANADIAN SYLLABICS WEST-CREE LWI","block":"Unified Canadian Aboriginal Syllabics","script":"Unknown","category":"Lo","kind":"glyph"},{"cp":5344,"name":"CANADIAN SYLLABICS LWII","block":"Unified Canadian Aboriginal Syllabics","script":"Unknown","category":"Lo","kind":"glyph"},{"cp":5345,"name":"CANADIAN SYLLABICS WEST-CREE LWII","block":"Unified Canadian Aboriginal Syllabics","script":"Unknown","category":"Lo","kind":"glyph"},{"cp":5346,"name":"CANADIAN SYLLABICS LWO","block":"Unified Canadian Aboriginal Syllabics","script":"Unknown","category":"Lo","kind":"glyph"},{"cp":5347,"name":"CANADIAN SYLLABICS WEST-CREE LWO","block":"Unified Canadian Aboriginal Syllabics","script":"Unknown","category":"Lo","kind":"glyph"},{"cp":5348,"name":"CANADIAN SYLLABICS LWOO","block":"Unified Canadian Aboriginal Syllabics","script":"Unknown","category":"Lo","kind":"glyph"},{"cp":5349,"name":"CANADIAN SYLLABICS WEST-CREE LWOO","block":"Unified Canadian Aboriginal Syllabics","script":"Unknown","category":"Lo","kind":"glyph"},{"cp":5350,"name":"CANADIAN SYLLABICS LWA","block":"Unified Canadian Aboriginal Syllabics","script":"Unknown","category":"Lo","kind":"glyph"},{"cp":5351,"name":"CANADIAN SYLLABICS WEST-CREE LWA","block":"Unified Canadian Aboriginal Syllabics","script":"Unknown","category":"Lo","kind":"glyph"},{"cp":5352,"name":"CANADIAN SYLLABICS LWAA","block":"Unified Canadian Aboriginal Syllabics","script":"Unknown","category":"Lo","kind":"glyph"},{"cp":5353,"name":"CANADIAN SYLLABICS WEST-CREE LWAA","block":"Unified Canadian Aboriginal Syllabics","script":"Unknown","category":"Lo","kind":"glyph"},{"cp":5354,"name":"CANADIAN SYLLABICS L","block":"Unified Canadian Aboriginal Syllabics","script":"Unknown","category":"Lo","kind":"glyph"},{"cp":5355,"name":"CANADIAN SYLLABICS WEST-CREE L","block":"Unified Canadian Aboriginal Syllabics","script":"Unknown","category":"Lo","kind":"glyph"},{"cp":5356,"name":"CANADIAN SYLLABICS MEDIAL L","block":"Unified Canadian Aboriginal Syllabics","script":"Unknown","category":"Lo","kind":"glyph"},{"cp":5357,"name":"CANADIAN SYLLABICS SE","block":"Unified Canadian Aboriginal Syllabics","script":"Unknown","category":"Lo","kind":"glyph"},{"cp":5358,"name":"CANADIAN SYLLABICS SAAI","block":"Unified Canadian Aboriginal Syllabics","script":"Unknown","category":"Lo","kind":"glyph"},{"cp":5359,"name":"CANADIAN SYLLABICS SI","block":"Unified Canadian Aboriginal Syllabics","script":"Unknown","category":"Lo","kind":"glyph"},{"cp":5360,"name":"CANADIAN SYLLABICS SII","block":"Unified Canadian Aboriginal Syllabics","script":"Unknown","category":"Lo","kind":"glyph"},{"cp":5361,"name":"CANADIAN SYLLABICS SO","block":"Unified Canadian Aboriginal Syllabics","script":"Unknown","category":"Lo","kind":"glyph"},{"cp":5362,"name":"CANADIAN SYLLABICS SOO","block":"Unified Canadian Aboriginal Syllabics","script":"Unknown","category":"Lo","kind":"glyph"},{"cp":5363,"name":"CANADIAN SYLLABICS Y-CREE SOO","block":"Unified Canadian Aboriginal Syllabics","script":"Unknown","category":"Lo","kind":"glyph"},{"cp":5364,"name":"CANADIAN SYLLABICS SA","block":"Unified Canadian Aboriginal Syllabics","script":"Unknown","category":"Lo","kind":"glyph"},{"cp":5365,"name":"CANADIAN SYLLABICS SAA","block":"Unified Canadian Aboriginal Syllabics","script":"Unknown","category":"Lo","kind":"glyph"},{"cp":5366,"name":"CANADIAN SYLLABICS SWE","block":"Unified Canadian Aboriginal Syllabics","script":"Unknown","category":"Lo","kind":"glyph"},{"cp":5367,"name":"CANADIAN SYLLABICS WEST-CREE SWE","block":"Unified Canadian Aboriginal Syllabics","script":"Unknown","category":"Lo","kind":"glyph"},{"cp":5368,"name":"CANADIAN SYLLABICS SWI","block":"Unified Canadian Aboriginal Syllabics","script":"Unknown","category":"Lo","kind":"glyph"},{"cp":5369,"name":"CANADIAN SYLLABICS WEST-CREE SWI","block":"Unified Canadian Aboriginal Syllabics","script":"Unknown","category":"Lo","kind":"glyph"},{"cp":5370,"name":"CANADIAN SYLLABICS SWII","block":"Unified Canadian Aboriginal Syllabics","script":"Unknown","category":"Lo","kind":"glyph"},{"cp":5371,"name":"CANADIAN SYLLABICS WEST-CREE SWII","block":"Unified Canadian Aboriginal Syllabics","script":"Unknown","category":"Lo","kind":"glyph"},{"cp":5372,"name":"CANADIAN SYLLABICS SWO","block":"Unified Canadian Aboriginal Syllabics","script":"Unknown","category":"Lo","kind":"glyph"},{"cp":5373,"name":"CANADIAN SYLLABICS WEST-CREE SWO","block":"Unified Canadian Aboriginal Syllabics","script":"Unknown","category":"Lo","kind":"glyph"},{"cp":5374,"name":"CANADIAN SYLLABICS SWOO","block":"Unified Canadian Aboriginal Syllabics","script":"Unknown","category":"Lo","kind":"glyph"},{"cp":5375,"name":"CANADIAN SYLLABICS WEST-CREE SWOO","block":"Unified Canadian Aboriginal Syllabics","script":"Unknown","category":"Lo","kind":"glyph"},{"cp":5376,"name":"CANADIAN SYLLABICS SWA","block":"Unified Canadian Aboriginal Syllabics","script":"Unknown","category":"Lo","kind":"glyph"},{"cp":5377,"name":"CANADIAN SYLLABICS WEST-CREE SWA","block":"Unified Canadian Aboriginal Syllabics","script":"Unknown","category":"Lo","kind":"glyph"},{"cp":5378,"name":"CANADIAN SYLLABICS SWAA","block":"Unified Canadian Aboriginal Syllabics","script":"Unknown","category":"Lo","kind":"glyph"},{"cp":5379,"name":"CANADIAN SYLLABICS WEST-CREE SWAA","block":"Unified Canadian Aboriginal Syllabics","script":"Unknown","category":"Lo","kind":"glyph"},{"cp":5380,"name":"CANADIAN SYLLABICS NASKAPI SWAA","block":"Unified Canadian Aboriginal Syllabics","script":"Unknown","category":"Lo","kind":"glyph"},{"cp":5381,"name":"CANADIAN SYLLABICS S","block":"Unified Canadian Aboriginal Syllabics","script":"Unknown","category":"Lo","kind":"glyph"},{"cp":5382,"name":"CANADIAN SYLLABICS ATHAPASCAN S","block":"Unified Canadian Aboriginal Syllabics","script":"Unknown","category":"Lo","kind":"glyph"},{"cp":5383,"name":"CANADIAN SYLLABICS SW","block":"Unified Canadian Aboriginal Syllabics","script":"Unknown","category":"Lo","kind":"glyph"},{"cp":5384,"name":"CANADIAN SYLLABICS BLACKFOOT S","block":"Unified Canadian Aboriginal Syllabics","script":"Unknown","category":"Lo","kind":"glyph"},{"cp":5385,"name":"CANADIAN SYLLABICS MOOSE-CREE SK","block":"Unified Canadian Aboriginal Syllabics","script":"Unknown","category":"Lo","kind":"glyph"},{"cp":5386,"name":"CANADIAN SYLLABICS NASKAPI SKW","block":"Unified Canadian Aboriginal Syllabics","script":"Unknown","category":"Lo","kind":"glyph"},{"cp":5387,"name":"CANADIAN SYLLABICS NASKAPI S-W","block":"Unified Canadian Aboriginal Syllabics","script":"Unknown","category":"Lo","kind":"glyph"},{"cp":5388,"name":"CANADIAN SYLLABICS NASKAPI SPWA","block":"Unified Canadian Aboriginal Syllabics","script":"Unknown","category":"Lo","kind":"glyph"},{"cp":5389,"name":"CANADIAN SYLLABICS NASKAPI STWA","block":"Unified Canadian Aboriginal Syllabics","script":"Unknown","category":"Lo","kind":"glyph"},{"cp":5390,"name":"CANADIAN SYLLABICS NASKAPI SKWA","block":"Unified Canadian Aboriginal Syllabics","script":"Unknown","category":"Lo","kind":"glyph"},{"cp":5391,"name":"CANADIAN SYLLABICS NASKAPI SCWA","block":"Unified Canadian Aboriginal Syllabics","script":"Unknown","category":"Lo","kind":"glyph"},{"cp":5392,"name":"CANADIAN SYLLABICS SHE","block":"Unified Canadian Aboriginal Syllabics","script":"Unknown","category":"Lo","kind":"glyph"},{"cp":5393,"name":"CANADIAN SYLLABICS SHI","block":"Unified Canadian Aboriginal Syllabics","script":"Unknown","category":"Lo","kind":"glyph"},{"cp":5394,"name":"CANADIAN SYLLABICS SHII","block":"Unified Canadian Aboriginal Syllabics","script":"Unknown","category":"Lo","kind":"glyph"},{"cp":5395,"name":"CANADIAN SYLLABICS SHO","block":"Unified Canadian Aboriginal Syllabics","script":"Unknown","category":"Lo","kind":"glyph"},{"cp":5396,"name":"CANADIAN SYLLABICS SHOO","block":"Unified Canadian Aboriginal Syllabics","script":"Unknown","category":"Lo","kind":"glyph"},{"cp":5397,"name":"CANADIAN SYLLABICS SHA","block":"Unified Canadian Aboriginal Syllabics","script":"Unknown","category":"Lo","kind":"glyph"},{"cp":5398,"name":"CANADIAN SYLLABICS SHAA","block":"Unified Canadian Aboriginal Syllabics","script":"Unknown","category":"Lo","kind":"glyph"},{"cp":5399,"name":"CANADIAN SYLLABICS SHWE","block":"Unified Canadian Aboriginal Syllabics","script":"Unknown","category":"Lo","kind":"glyph"},{"cp":5400,"name":"CANADIAN SYLLABICS WEST-CREE SHWE","block":"Unified Canadian Aboriginal Syllabics","script":"Unknown","category":"Lo","kind":"glyph"},{"cp":5401,"name":"CANADIAN SYLLABICS SHWI","block":"Unified Canadian Aboriginal Syllabics","script":"Unknown","category":"Lo","kind":"glyph"},{"cp":5402,"name":"CANADIAN SYLLABICS WEST-CREE SHWI","block":"Unified Canadian Aboriginal Syllabics","script":"Unknown","category":"Lo","kind":"glyph"},{"cp":5403,"name":"CANADIAN SYLLABICS SHWII","block":"Unified Canadian Aboriginal Syllabics","script":"Unknown","category":"Lo","kind":"glyph"},{"cp":5404,"name":"CANADIAN SYLLABICS WEST-CREE SHWII","block":"Unified Canadian Aboriginal Syllabics","script":"Unknown","category":"Lo","kind":"glyph"},{"cp":5405,"name":"CANADIAN SYLLABICS SHWO","block":"Unified Canadian Aboriginal Syllabics","script":"Unknown","category":"Lo","kind":"glyph"},{"cp":5406,"name":"CANADIAN SYLLABICS WEST-CREE SHWO","block":"Unified Canadian Aboriginal Syllabics","script":"Unknown","category":"Lo","kind":"glyph"},{"cp":5407,"name":"CANADIAN SYLLABICS SHWOO","block":"Unified Canadian Aboriginal Syllabics","script":"Unknown","category":"Lo","kind":"glyph"},{"cp":5408,"name":"CANADIAN SYLLABICS WEST-CREE SHWOO","block":"Unified Canadian Aboriginal Syllabics","script":"Unknown","category":"Lo","kind":"glyph"},{"cp":5409,"name":"CANADIAN SYLLABICS SHWA","block":"Unified Canadian Aboriginal Syllabics","script":"Unknown","category":"Lo","kind":"glyph"},{"cp":5410,"name":"CANADIAN SYLLABICS WEST-CREE SHWA","block":"Unified Canadian Aboriginal Syllabics","script":"Unknown","category":"Lo","kind":"glyph"},{"cp":5411,"name":"CANADIAN SYLLABICS SHWAA","block":"Unified Canadian Aboriginal Syllabics","script":"Unknown","category":"Lo","kind":"glyph"},{"cp":5412,"name":"CANADIAN SYLLABICS WEST-CREE SHWAA","block":"Unified Canadian Aboriginal Syllabics","script":"Unknown","category":"Lo","kind":"glyph"},{"cp":5413,"name":"CANADIAN SYLLABICS SH","block":"Unified Canadian Aboriginal Syllabics","script":"Unknown","category":"Lo","kind":"glyph"},{"cp":5414,"name":"CANADIAN SYLLABICS YE","block":"Unified Canadian Aboriginal Syllabics","script":"Unknown","category":"Lo","kind":"glyph"},{"cp":5415,"name":"CANADIAN SYLLABICS YAAI","block":"Unified Canadian Aboriginal Syllabics","script":"Unknown","category":"Lo","kind":"glyph"},{"cp":5416,"name":"CANADIAN SYLLABICS YI","block":"Unified Canadian Aboriginal Syllabics","script":"Unknown","category":"Lo","kind":"glyph"},{"cp":5417,"name":"CANADIAN SYLLABICS YII","block":"Unified Canadian Aboriginal Syllabics","script":"Unknown","category":"Lo","kind":"glyph"},{"cp":5418,"name":"CANADIAN SYLLABICS YO","block":"Unified Canadian Aboriginal Syllabics","script":"Unknown","category":"Lo","kind":"glyph"},{"cp":5419,"name":"CANADIAN SYLLABICS YOO","block":"Unified Canadian Aboriginal Syllabics","script":"Unknown","category":"Lo","kind":"glyph"},{"cp":5420,"name":"CANADIAN SYLLABICS Y-CREE YOO","block":"Unified Canadian Aboriginal Syllabics","script":"Unknown","category":"Lo","kind":"glyph"},{"cp":5421,"name":"CANADIAN SYLLABICS YA","block":"Unified Canadian Aboriginal Syllabics","script":"Unknown","category":"Lo","kind":"glyph"},{"cp":5422,"name":"CANADIAN SYLLABICS YAA","block":"Unified Canadian Aboriginal Syllabics","script":"Unknown","category":"Lo","kind":"glyph"},{"cp":5423,"name":"CANADIAN SYLLABICS YWE","block":"Unified Canadian Aboriginal Syllabics","script":"Unknown","category":"Lo","kind":"glyph"},{"cp":5424,"name":"CANADIAN SYLLABICS WEST-CREE YWE","block":"Unified Canadian Aboriginal Syllabics","script":"Unknown","category":"Lo","kind":"glyph"},{"cp":5425,"name":"CANADIAN SYLLABICS YWI","block":"Unified Canadian Aboriginal Syllabics","script":"Unknown","category":"Lo","kind":"glyph"},{"cp":5426,"name":"CANADIAN SYLLABICS WEST-CREE YWI","block":"Unified Canadian Aboriginal Syllabics","script":"Unknown","category":"Lo","kind":"glyph"},{"cp":5427,"name":"CANADIAN SYLLABICS YWII","block":"Unified Canadian Aboriginal Syllabics","script":"Unknown","category":"Lo","kind":"glyph"},{"cp":5428,"name":"CANADIAN SYLLABICS WEST-CREE YWII","block":"Unified Canadian Aboriginal Syllabics","script":"Unknown","category":"Lo","kind":"glyph"},{"cp":5429,"name":"CANADIAN SYLLABICS YWO","block":"Unified Canadian Aboriginal Syllabics","script":"Unknown","category":"Lo","kind":"glyph"},{"cp":5430,"name":"CANADIAN SYLLABICS WEST-CREE YWO","block":"Unified Canadian Aboriginal Syllabics","script":"Unknown","category":"Lo","kind":"glyph"},{"cp":5431,"name":"CANADIAN SYLLABICS YWOO","block":"Unified Canadian Aboriginal Syllabics","script":"Unknown","category":"Lo","kind":"glyph"},{"cp":5432,"name":"CANADIAN SYLLABICS WEST-CREE YWOO","block":"Unified Canadian Aboriginal Syllabics","script":"Unknown","category":"Lo","kind":"glyph"},{"cp":5433,"name":"CANADIAN SYLLABICS YWA","block":"Unified Canadian Aboriginal Syllabics","script":"Unknown","category":"Lo","kind":"glyph"},{"cp":5434,"name":"CANADIAN SYLLABICS WEST-CREE YWA","block":"Unified Canadian Aboriginal Syllabics","script":"Unknown","category":"Lo","kind":"glyph"},{"cp":5435,"name":"CANADIAN SYLLABICS YWAA","block":"Unified Canadian Aboriginal Syllabics","script":"Unknown","category":"Lo","kind":"glyph"},{"cp":5436,"name":"CANADIAN SYLLABICS WEST-CREE YWAA","block":"Unified Canadian Aboriginal Syllabics","script":"Unknown","category":"Lo","kind":"glyph"},{"cp":5437,"name":"CANADIAN SYLLABICS NASKAPI YWAA","block":"Unified Canadian Aboriginal Syllabics","script":"Unknown","category":"Lo","kind":"glyph"},{"cp":5438,"name":"CANADIAN SYLLABICS Y","block":"Unified Canadian Aboriginal Syllabics","script":"Unknown","category":"Lo","kind":"glyph"},{"cp":5439,"name":"CANADIAN SYLLABICS BIBLE-CREE Y","block":"Unified Canadian Aboriginal Syllabics","script":"Unknown","category":"Lo","kind":"glyph"},{"cp":5440,"name":"CANADIAN SYLLABICS WEST-CREE Y","block":"Unified Canadian Aboriginal Syllabics","script":"Unknown","category":"Lo","kind":"glyph"},{"cp":5441,"name":"CANADIAN SYLLABICS SAYISI YI","block":"Unified Canadian Aboriginal Syllabics","script":"Unknown","category":"Lo","kind":"glyph"},{"cp":5442,"name":"CANADIAN SYLLABICS RE","block":"Unified Canadian Aboriginal Syllabics","script":"Unknown","category":"Lo","kind":"glyph"},{"cp":5443,"name":"CANADIAN SYLLABICS R-CREE RE","block":"Unified Canadian Aboriginal Syllabics","script":"Unknown","category":"Lo","kind":"glyph"},{"cp":5444,"name":"CANADIAN SYLLABICS WEST-CREE LE","block":"Unified Canadian Aboriginal Syllabics","script":"Unknown","category":"Lo","kind":"glyph"},{"cp":5445,"name":"CANADIAN SYLLABICS RAAI","block":"Unified Canadian Aboriginal Syllabics","script":"Unknown","category":"Lo","kind":"glyph"},{"cp":5446,"name":"CANADIAN SYLLABICS RI","block":"Unified Canadian Aboriginal Syllabics","script":"Unknown","category":"Lo","kind":"glyph"},{"cp":5447,"name":"CANADIAN SYLLABICS RII","block":"Unified Canadian Aboriginal Syllabics","script":"Unknown","category":"Lo","kind":"glyph"},{"cp":5448,"name":"CANADIAN SYLLABICS RO","block":"Unified Canadian Aboriginal Syllabics","script":"Unknown","category":"Lo","kind":"glyph"},{"cp":5449,"name":"CANADIAN SYLLABICS ROO","block":"Unified Canadian Aboriginal Syllabics","script":"Unknown","category":"Lo","kind":"glyph"},{"cp":5450,"name":"CANADIAN SYLLABICS WEST-CREE LO","block":"Unified Canadian Aboriginal Syllabics","script":"Unknown","category":"Lo","kind":"glyph"},{"cp":5451,"name":"CANADIAN SYLLABICS RA","block":"Unified Canadian Aboriginal Syllabics","script":"Unknown","category":"Lo","kind":"glyph"},{"cp":5452,"name":"CANADIAN SYLLABICS RAA","block":"Unified Canadian Aboriginal Syllabics","script":"Unknown","category":"Lo","kind":"glyph"},{"cp":5453,"name":"CANADIAN SYLLABICS WEST-CREE LA","block":"Unified Canadian Aboriginal Syllabics","script":"Unknown","category":"Lo","kind":"glyph"},{"cp":5454,"name":"CANADIAN SYLLABICS RWAA","block":"Unified Canadian Aboriginal Syllabics","script":"Unknown","category":"Lo","kind":"glyph"},{"cp":5455,"name":"CANADIAN SYLLABICS WEST-CREE RWAA","block":"Unified Canadian Aboriginal Syllabics","script":"Unknown","category":"Lo","kind":"glyph"},{"cp":5456,"name":"CANADIAN SYLLABICS R","block":"Unified Canadian Aboriginal Syllabics","script":"Unknown","category":"Lo","kind":"glyph"},{"cp":5457,"name":"CANADIAN SYLLABICS WEST-CREE R","block":"Unified Canadian Aboriginal Syllabics","script":"Unknown","category":"Lo","kind":"glyph"},{"cp":5458,"name":"CANADIAN SYLLABICS MEDIAL R","block":"Unified Canadian Aboriginal Syllabics","script":"Unknown","category":"Lo","kind":"glyph"},{"cp":5459,"name":"CANADIAN SYLLABICS FE","block":"Unified Canadian Aboriginal Syllabics","script":"Unknown","category":"Lo","kind":"glyph"},{"cp":5460,"name":"CANADIAN SYLLABICS FAAI","block":"Unified Canadian Aboriginal Syllabics","script":"Unknown","category":"Lo","kind":"glyph"},{"cp":5461,"name":"CANADIAN SYLLABICS FI","block":"Unified Canadian Aboriginal Syllabics","script":"Unknown","category":"Lo","kind":"glyph"},{"cp":5462,"name":"CANADIAN SYLLABICS FII","block":"Unified Canadian Aboriginal Syllabics","script":"Unknown","category":"Lo","kind":"glyph"},{"cp":5463,"name":"CANADIAN SYLLABICS FO","block":"Unified Canadian Aboriginal Syllabics","script":"Unknown","category":"Lo","kind":"glyph"},{"cp":5464,"name":"CANADIAN SYLLABICS FOO","block":"Unified Canadian Aboriginal Syllabics","script":"Unknown","category":"Lo","kind":"glyph"},{"cp":5465,"name":"CANADIAN SYLLABICS FA","block":"Unified Canadian Aboriginal Syllabics","script":"Unknown","category":"Lo","kind":"glyph"},{"cp":5466,"name":"CANADIAN SYLLABICS FAA","block":"Unified Canadian Aboriginal Syllabics","script":"Unknown","category":"Lo","kind":"glyph"},{"cp":5467,"name":"CANADIAN SYLLABICS FWAA","block":"Unified Canadian Aboriginal Syllabics","script":"Unknown","category":"Lo","kind":"glyph"},{"cp":5468,"name":"CANADIAN SYLLABICS WEST-CREE FWAA","block":"Unified Canadian Aboriginal Syllabics","script":"Unknown","category":"Lo","kind":"glyph"},{"cp":5469,"name":"CANADIAN SYLLABICS F","block":"Unified Canadian Aboriginal Syllabics","script":"Unknown","category":"Lo","kind":"glyph"},{"cp":5470,"name":"CANADIAN SYLLABICS THE","block":"Unified Canadian Aboriginal Syllabics","script":"Unknown","category":"Lo","kind":"glyph"},{"cp":5471,"name":"CANADIAN SYLLABICS N-CREE THE","block":"Unified Canadian Aboriginal Syllabics","script":"Unknown","category":"Lo","kind":"glyph"},{"cp":5472,"name":"CANADIAN SYLLABICS THI","block":"Unified Canadian Aboriginal Syllabics","script":"Unknown","category":"Lo","kind":"glyph"},{"cp":5473,"name":"CANADIAN SYLLABICS N-CREE THI","block":"Unified Canadian Aboriginal Syllabics","script":"Unknown","category":"Lo","kind":"glyph"},{"cp":5474,"name":"CANADIAN SYLLABICS THII","block":"Unified Canadian Aboriginal Syllabics","script":"Unknown","category":"Lo","kind":"glyph"},{"cp":5475,"name":"CANADIAN SYLLABICS N-CREE THII","block":"Unified Canadian Aboriginal Syllabics","script":"Unknown","category":"Lo","kind":"glyph"},{"cp":5476,"name":"CANADIAN SYLLABICS THO","block":"Unified Canadian Aboriginal Syllabics","script":"Unknown","category":"Lo","kind":"glyph"},{"cp":5477,"name":"CANADIAN SYLLABICS THOO","block":"Unified Canadian Aboriginal Syllabics","script":"Unknown","category":"Lo","kind":"glyph"},{"cp":5478,"name":"CANADIAN SYLLABICS THA","block":"Unified Canadian Aboriginal Syllabics","script":"Unknown","category":"Lo","kind":"glyph"},{"cp":5479,"name":"CANADIAN SYLLABICS THAA","block":"Unified Canadian Aboriginal Syllabics","script":"Unknown","category":"Lo","kind":"glyph"},{"cp":5480,"name":"CANADIAN SYLLABICS THWAA","block":"Unified Canadian Aboriginal Syllabics","script":"Unknown","category":"Lo","kind":"glyph"},{"cp":5481,"name":"CANADIAN SYLLABICS WEST-CREE THWAA","block":"Unified Canadian Aboriginal Syllabics","script":"Unknown","category":"Lo","kind":"glyph"},{"cp":5482,"name":"CANADIAN SYLLABICS TH","block":"Unified Canadian Aboriginal Syllabics","script":"Unknown","category":"Lo","kind":"glyph"},{"cp":5483,"name":"CANADIAN SYLLABICS TTHE","block":"Unified Canadian Aboriginal Syllabics","script":"Unknown","category":"Lo","kind":"glyph"},{"cp":5484,"name":"CANADIAN SYLLABICS TTHI","block":"Unified Canadian Aboriginal Syllabics","script":"Unknown","category":"Lo","kind":"glyph"},{"cp":5485,"name":"CANADIAN SYLLABICS TTHO","block":"Unified Canadian Aboriginal Syllabics","script":"Unknown","category":"Lo","kind":"glyph"},{"cp":5486,"name":"CANADIAN SYLLABICS TTHA","block":"Unified Canadian Aboriginal Syllabics","script":"Unknown","category":"Lo","kind":"glyph"},{"cp":5487,"name":"CANADIAN SYLLABICS TTH","block":"Unified Canadian Aboriginal Syllabics","script":"Unknown","category":"Lo","kind":"glyph"},{"cp":5488,"name":"CANADIAN SYLLABICS TYE","block":"Unified Canadian Aboriginal Syllabics","script":"Unknown","category":"Lo","kind":"glyph"},{"cp":5489,"name":"CANADIAN SYLLABICS TYI","block":"Unified Canadian Aboriginal Syllabics","script":"Unknown","category":"Lo","kind":"glyph"},{"cp":5490,"name":"CANADIAN SYLLABICS TYO","block":"Unified Canadian Aboriginal Syllabics","script":"Unknown","category":"Lo","kind":"glyph"},{"cp":5491,"name":"CANADIAN SYLLABICS TYA","block":"Unified Canadian Aboriginal Syllabics","script":"Unknown","category":"Lo","kind":"glyph"},{"cp":5492,"name":"CANADIAN SYLLABICS NUNAVIK HE","block":"Unified Canadian Aboriginal Syllabics","script":"Unknown","category":"Lo","kind":"glyph"},{"cp":5493,"name":"CANADIAN SYLLABICS NUNAVIK HI","block":"Unified Canadian Aboriginal Syllabics","script":"Unknown","category":"Lo","kind":"glyph"},{"cp":5494,"name":"CANADIAN SYLLABICS NUNAVIK HII","block":"Unified Canadian Aboriginal Syllabics","script":"Unknown","category":"Lo","kind":"glyph"},{"cp":5495,"name":"CANADIAN SYLLABICS NUNAVIK HO","block":"Unified Canadian Aboriginal Syllabics","script":"Unknown","category":"Lo","kind":"glyph"},{"cp":5496,"name":"CANADIAN SYLLABICS NUNAVIK HOO","block":"Unified Canadian Aboriginal Syllabics","script":"Unknown","category":"Lo","kind":"glyph"},{"cp":5497,"name":"CANADIAN SYLLABICS NUNAVIK HA","block":"Unified Canadian Aboriginal Syllabics","script":"Unknown","category":"Lo","kind":"glyph"},{"cp":5498,"name":"CANADIAN SYLLABICS NUNAVIK HAA","block":"Unified Canadian Aboriginal Syllabics","script":"Unknown","category":"Lo","kind":"glyph"},{"cp":5499,"name":"CANADIAN SYLLABICS NUNAVIK H","block":"Unified Canadian Aboriginal Syllabics","script":"Unknown","category":"Lo","kind":"glyph"},{"cp":5500,"name":"CANADIAN SYLLABICS NUNAVUT H","block":"Unified Canadian Aboriginal Syllabics","script":"Unknown","category":"Lo","kind":"glyph"},{"cp":5501,"name":"CANADIAN SYLLABICS HK","block":"Unified Canadian Aboriginal Syllabics","script":"Unknown","category":"Lo","kind":"glyph"},{"cp":5502,"name":"CANADIAN SYLLABICS QAAI","block":"Unified Canadian Aboriginal Syllabics","script":"Unknown","category":"Lo","kind":"glyph"},{"cp":5503,"name":"CANADIAN SYLLABICS QI","block":"Unified Canadian Aboriginal Syllabics","script":"Unknown","category":"Lo","kind":"glyph"},{"cp":5504,"name":"CANADIAN SYLLABICS QII","block":"Unified Canadian Aboriginal Syllabics","script":"Unknown","category":"Lo","kind":"glyph"},{"cp":5505,"name":"CANADIAN SYLLABICS QO","block":"Unified Canadian Aboriginal Syllabics","script":"Unknown","category":"Lo","kind":"glyph"},{"cp":5506,"name":"CANADIAN SYLLABICS QOO","block":"Unified Canadian Aboriginal Syllabics","script":"Unknown","category":"Lo","kind":"glyph"},{"cp":5507,"name":"CANADIAN SYLLABICS QA","block":"Unified Canadian Aboriginal Syllabics","script":"Unknown","category":"Lo","kind":"glyph"},{"cp":5508,"name":"CANADIAN SYLLABICS QAA","block":"Unified Canadian Aboriginal Syllabics","script":"Unknown","category":"Lo","kind":"glyph"},{"cp":5509,"name":"CANADIAN SYLLABICS Q","block":"Unified Canadian Aboriginal Syllabics","script":"Unknown","category":"Lo","kind":"glyph"},{"cp":5510,"name":"CANADIAN SYLLABICS TLHE","block":"Unified Canadian Aboriginal Syllabics","script":"Unknown","category":"Lo","kind":"glyph"},{"cp":5511,"name":"CANADIAN SYLLABICS TLHI","block":"Unified Canadian Aboriginal Syllabics","script":"Unknown","category":"Lo","kind":"glyph"},{"cp":5512,"name":"CANADIAN SYLLABICS TLHO","block":"Unified Canadian Aboriginal Syllabics","script":"Unknown","category":"Lo","kind":"glyph"},{"cp":5513,"name":"CANADIAN SYLLABICS TLHA","block":"Unified Canadian Aboriginal Syllabics","script":"Unknown","category":"Lo","kind":"glyph"},{"cp":5514,"name":"CANADIAN SYLLABICS WEST-CREE RE","block":"Unified Canadian Aboriginal Syllabics","script":"Unknown","category":"Lo","kind":"glyph"},{"cp":5515,"name":"CANADIAN SYLLABICS WEST-CREE RI","block":"Unified Canadian Aboriginal Syllabics","script":"Unknown","category":"Lo","kind":"glyph"},{"cp":5516,"name":"CANADIAN SYLLABICS WEST-CREE RO","block":"Unified Canadian Aboriginal Syllabics","script":"Unknown","category":"Lo","kind":"glyph"},{"cp":5517,"name":"CANADIAN SYLLABICS WEST-CREE RA","block":"Unified Canadian Aboriginal Syllabics","script":"Unknown","category":"Lo","kind":"glyph"},{"cp":5518,"name":"CANADIAN SYLLABICS NGAAI","block":"Unified Canadian Aboriginal Syllabics","script":"Unknown","category":"Lo","kind":"glyph"},{"cp":5519,"name":"CANADIAN SYLLABICS NGI","block":"Unified Canadian Aboriginal Syllabics","script":"Unknown","category":"Lo","kind":"glyph"},{"cp":5520,"name":"CANADIAN SYLLABICS NGII","block":"Unified Canadian Aboriginal Syllabics","script":"Unknown","category":"Lo","kind":"glyph"},{"cp":5521,"name":"CANADIAN SYLLABICS NGO","block":"Unified Canadian Aboriginal Syllabics","script":"Unknown","category":"Lo","kind":"glyph"},{"cp":5522,"name":"CANADIAN SYLLABICS NGOO","block":"Unified Canadian Aboriginal Syllabics","script":"Unknown","category":"Lo","kind":"glyph"},{"cp":5523,"name":"CANADIAN SYLLABICS NGA","block":"Unified Canadian Aboriginal Syllabics","script":"Unknown","category":"Lo","kind":"glyph"},{"cp":5524,"name":"CANADIAN SYLLABICS NGAA","block":"Unified Canadian Aboriginal Syllabics","script":"Unknown","category":"Lo","kind":"glyph"},{"cp":5525,"name":"CANADIAN SYLLABICS NG","block":"Unified Canadian Aboriginal Syllabics","script":"Unknown","category":"Lo","kind":"glyph"},{"cp":5526,"name":"CANADIAN SYLLABICS NNG","block":"Unified Canadian Aboriginal Syllabics","script":"Unknown","category":"Lo","kind":"glyph"},{"cp":5527,"name":"CANADIAN SYLLABICS SAYISI SHE","block":"Unified Canadian Aboriginal Syllabics","script":"Unknown","category":"Lo","kind":"glyph"},{"cp":5528,"name":"CANADIAN SYLLABICS SAYISI SHI","block":"Unified Canadian Aboriginal Syllabics","script":"Unknown","category":"Lo","kind":"glyph"},{"cp":5529,"name":"CANADIAN SYLLABICS SAYISI SHO","block":"Unified Canadian Aboriginal Syllabics","script":"Unknown","category":"Lo","kind":"glyph"},{"cp":5530,"name":"CANADIAN SYLLABICS SAYISI SHA","block":"Unified Canadian Aboriginal Syllabics","script":"Unknown","category":"Lo","kind":"glyph"},{"cp":5531,"name":"CANADIAN SYLLABICS WOODS-CREE THE","block":"Unified Canadian Aboriginal Syllabics","script":"Unknown","category":"Lo","kind":"glyph"},{"cp":5532,"name":"CANADIAN SYLLABICS WOODS-CREE THI","block":"Unified Canadian Aboriginal Syllabics","script":"Unknown","category":"Lo","kind":"glyph"},{"cp":5533,"name":"CANADIAN SYLLABICS WOODS-CREE THO","block":"Unified Canadian Aboriginal Syllabics","script":"Unknown","category":"Lo","kind":"glyph"},{"cp":5534,"name":"CANADIAN SYLLABICS WOODS-CREE THA","block":"Unified Canadian Aboriginal Syllabics","script":"Unknown","category":"Lo","kind":"glyph"},{"cp":5535,"name":"CANADIAN SYLLABICS WOODS-CREE TH","block":"Unified Canadian Aboriginal Syllabics","script":"Unknown","category":"Lo","kind":"glyph"},{"cp":5536,"name":"CANADIAN SYLLABICS LHI","block":"Unified Canadian Aboriginal Syllabics","script":"Unknown","category":"Lo","kind":"glyph"},{"cp":5537,"name":"CANADIAN SYLLABICS LHII","block":"Unified Canadian Aboriginal Syllabics","script":"Unknown","category":"Lo","kind":"glyph"},{"cp":5538,"name":"CANADIAN SYLLABICS LHO","block":"Unified Canadian Aboriginal Syllabics","script":"Unknown","category":"Lo","kind":"glyph"},{"cp":5539,"name":"CANADIAN SYLLABICS LHOO","block":"Unified Canadian Aboriginal Syllabics","script":"Unknown","category":"Lo","kind":"glyph"},{"cp":5540,"name":"CANADIAN SYLLABICS LHA","block":"Unified Canadian Aboriginal Syllabics","script":"Unknown","category":"Lo","kind":"glyph"},{"cp":5541,"name":"CANADIAN SYLLABICS LHAA","block":"Unified Canadian Aboriginal Syllabics","script":"Unknown","category":"Lo","kind":"glyph"},{"cp":5542,"name":"CANADIAN SYLLABICS LH","block":"Unified Canadian Aboriginal Syllabics","script":"Unknown","category":"Lo","kind":"glyph"},{"cp":5543,"name":"CANADIAN SYLLABICS TH-CREE THE","block":"Unified Canadian Aboriginal Syllabics","script":"Unknown","category":"Lo","kind":"glyph"},{"cp":5544,"name":"CANADIAN SYLLABICS TH-CREE THI","block":"Unified Canadian Aboriginal Syllabics","script":"Unknown","category":"Lo","kind":"glyph"},{"cp":5545,"name":"CANADIAN SYLLABICS TH-CREE THII","block":"Unified Canadian Aboriginal Syllabics","script":"Unknown","category":"Lo","kind":"glyph"},{"cp":5546,"name":"CANADIAN SYLLABICS TH-CREE THO","block":"Unified Canadian Aboriginal Syllabics","script":"Unknown","category":"Lo","kind":"glyph"},{"cp":5547,"name":"CANADIAN SYLLABICS TH-CREE THOO","block":"Unified Canadian Aboriginal Syllabics","script":"Unknown","category":"Lo","kind":"glyph"},{"cp":5548,"name":"CANADIAN SYLLABICS TH-CREE THA","block":"Unified Canadian Aboriginal Syllabics","script":"Unknown","category":"Lo","kind":"glyph"},{"cp":5549,"name":"CANADIAN SYLLABICS TH-CREE THAA","block":"Unified Canadian Aboriginal Syllabics","script":"Unknown","category":"Lo","kind":"glyph"},{"cp":5550,"name":"CANADIAN SYLLABICS TH-CREE TH","block":"Unified Canadian Aboriginal Syllabics","script":"Unknown","category":"Lo","kind":"glyph"},{"cp":5551,"name":"CANADIAN SYLLABICS AIVILIK B","block":"Unified Canadian Aboriginal Syllabics","script":"Unknown","category":"Lo","kind":"glyph"},{"cp":5552,"name":"CANADIAN SYLLABICS BLACKFOOT E","block":"Unified Canadian Aboriginal Syllabics","script":"Unknown","category":"Lo","kind":"glyph"},{"cp":5553,"name":"CANADIAN SYLLABICS BLACKFOOT I","block":"Unified Canadian Aboriginal Syllabics","script":"Unknown","category":"Lo","kind":"glyph"},{"cp":5554,"name":"CANADIAN SYLLABICS BLACKFOOT O","block":"Unified Canadian Aboriginal Syllabics","script":"Unknown","category":"Lo","kind":"glyph"},{"cp":5555,"name":"CANADIAN SYLLABICS BLACKFOOT A","block":"Unified Canadian Aboriginal Syllabics","script":"Unknown","category":"Lo","kind":"glyph"},{"cp":5556,"name":"CANADIAN SYLLABICS BLACKFOOT WE","block":"Unified Canadian Aboriginal Syllabics","script":"Unknown","category":"Lo","kind":"glyph"},{"cp":5557,"name":"CANADIAN SYLLABICS BLACKFOOT WI","block":"Unified Canadian Aboriginal Syllabics","script":"Unknown","category":"Lo","kind":"glyph"},{"cp":5558,"name":"CANADIAN SYLLABICS BLACKFOOT WO","block":"Unified Canadian Aboriginal Syllabics","script":"Unknown","category":"Lo","kind":"glyph"},{"cp":5559,"name":"CANADIAN SYLLABICS BLACKFOOT WA","block":"Unified Canadian Aboriginal Syllabics","script":"Unknown","category":"Lo","kind":"glyph"},{"cp":5560,"name":"CANADIAN SYLLABICS BLACKFOOT NE","block":"Unified Canadian Aboriginal Syllabics","script":"Unknown","category":"Lo","kind":"glyph"},{"cp":5561,"name":"CANADIAN SYLLABICS BLACKFOOT NI","block":"Unified Canadian Aboriginal Syllabics","script":"Unknown","category":"Lo","kind":"glyph"},{"cp":5562,"name":"CANADIAN SYLLABICS BLACKFOOT NO","block":"Unified Canadian Aboriginal Syllabics","script":"Unknown","category":"Lo","kind":"glyph"},{"cp":5563,"name":"CANADIAN SYLLABICS BLACKFOOT NA","block":"Unified Canadian Aboriginal Syllabics","script":"Unknown","category":"Lo","kind":"glyph"},{"cp":5564,"name":"CANADIAN SYLLABICS BLACKFOOT KE","block":"Unified Canadian Aboriginal Syllabics","script":"Unknown","category":"Lo","kind":"glyph"},{"cp":5565,"name":"CANADIAN SYLLABICS BLACKFOOT KI","block":"Unified Canadian Aboriginal Syllabics","script":"Unknown","category":"Lo","kind":"glyph"},{"cp":5566,"name":"CANADIAN SYLLABICS BLACKFOOT KO","block":"Unified Canadian Aboriginal Syllabics","script":"Unknown","category":"Lo","kind":"glyph"},{"cp":5567,"name":"CANADIAN SYLLABICS BLACKFOOT KA","block":"Unified Canadian Aboriginal Syllabics","script":"Unknown","category":"Lo","kind":"glyph"},{"cp":5568,"name":"CANADIAN SYLLABICS SAYISI HE","block":"Unified Canadian Aboriginal Syllabics","script":"Unknown","category":"Lo","kind":"glyph"},{"cp":5569,"name":"CANADIAN SYLLABICS SAYISI HI","block":"Unified Canadian Aboriginal Syllabics","script":"Unknown","category":"Lo","kind":"glyph"},{"cp":5570,"name":"CANADIAN SYLLABICS SAYISI HO","block":"Unified Canadian Aboriginal Syllabics","script":"Unknown","category":"Lo","kind":"glyph"},{"cp":5571,"name":"CANADIAN SYLLABICS SAYISI HA","block":"Unified Canadian Aboriginal Syllabics","script":"Unknown","category":"Lo","kind":"glyph"},{"cp":5572,"name":"CANADIAN SYLLABICS CARRIER GHU","block":"Unified Canadian Aboriginal Syllabics","script":"Unknown","category":"Lo","kind":"glyph"},{"cp":5573,"name":"CANADIAN SYLLABICS CARRIER GHO","block":"Unified Canadian Aboriginal Syllabics","script":"Unknown","category":"Lo","kind":"glyph"},{"cp":5574,"name":"CANADIAN SYLLABICS CARRIER GHE","block":"Unified Canadian Aboriginal Syllabics","script":"Unknown","category":"Lo","kind":"glyph"},{"cp":5575,"name":"CANADIAN SYLLABICS CARRIER GHEE","block":"Unified Canadian Aboriginal Syllabics","script":"Unknown","category":"Lo","kind":"glyph"},{"cp":5576,"name":"CANADIAN SYLLABICS CARRIER GHI","block":"Unified Canadian Aboriginal Syllabics","script":"Unknown","category":"Lo","kind":"glyph"},{"cp":5577,"name":"CANADIAN SYLLABICS CARRIER GHA","block":"Unified Canadian Aboriginal Syllabics","script":"Unknown","category":"Lo","kind":"glyph"},{"cp":5578,"name":"CANADIAN SYLLABICS CARRIER RU","block":"Unified Canadian Aboriginal Syllabics","script":"Unknown","category":"Lo","kind":"glyph"},{"cp":5579,"name":"CANADIAN SYLLABICS CARRIER RO","block":"Unified Canadian Aboriginal Syllabics","script":"Unknown","category":"Lo","kind":"glyph"},{"cp":5580,"name":"CANADIAN SYLLABICS CARRIER RE","block":"Unified Canadian Aboriginal Syllabics","script":"Unknown","category":"Lo","kind":"glyph"},{"cp":5581,"name":"CANADIAN SYLLABICS CARRIER REE","block":"Unified Canadian Aboriginal Syllabics","script":"Unknown","category":"Lo","kind":"glyph"},{"cp":5582,"name":"CANADIAN SYLLABICS CARRIER RI","block":"Unified Canadian Aboriginal Syllabics","script":"Unknown","category":"Lo","kind":"glyph"},{"cp":5583,"name":"CANADIAN SYLLABICS CARRIER RA","block":"Unified Canadian Aboriginal Syllabics","script":"Unknown","category":"Lo","kind":"glyph"},{"cp":5584,"name":"CANADIAN SYLLABICS CARRIER WU","block":"Unified Canadian Aboriginal Syllabics","script":"Unknown","category":"Lo","kind":"glyph"},{"cp":5585,"name":"CANADIAN SYLLABICS CARRIER WO","block":"Unified Canadian Aboriginal Syllabics","script":"Unknown","category":"Lo","kind":"glyph"},{"cp":5586,"name":"CANADIAN SYLLABICS CARRIER WE","block":"Unified Canadian Aboriginal Syllabics","script":"Unknown","category":"Lo","kind":"glyph"},{"cp":5587,"name":"CANADIAN SYLLABICS CARRIER WEE","block":"Unified Canadian Aboriginal Syllabics","script":"Unknown","category":"Lo","kind":"glyph"},{"cp":5588,"name":"CANADIAN SYLLABICS CARRIER WI","block":"Unified Canadian Aboriginal Syllabics","script":"Unknown","category":"Lo","kind":"glyph"},{"cp":5589,"name":"CANADIAN SYLLABICS CARRIER WA","block":"Unified Canadian Aboriginal Syllabics","script":"Unknown","category":"Lo","kind":"glyph"},{"cp":5590,"name":"CANADIAN SYLLABICS CARRIER HWU","block":"Unified Canadian Aboriginal Syllabics","script":"Unknown","category":"Lo","kind":"glyph"},{"cp":5591,"name":"CANADIAN SYLLABICS CARRIER HWO","block":"Unified Canadian Aboriginal Syllabics","script":"Unknown","category":"Lo","kind":"glyph"},{"cp":5592,"name":"CANADIAN SYLLABICS CARRIER HWE","block":"Unified Canadian Aboriginal Syllabics","script":"Unknown","category":"Lo","kind":"glyph"},{"cp":5593,"name":"CANADIAN SYLLABICS CARRIER HWEE","block":"Unified Canadian Aboriginal Syllabics","script":"Unknown","category":"Lo","kind":"glyph"},{"cp":5594,"name":"CANADIAN SYLLABICS CARRIER HWI","block":"Unified Canadian Aboriginal Syllabics","script":"Unknown","category":"Lo","kind":"glyph"},{"cp":5595,"name":"CANADIAN SYLLABICS CARRIER HWA","block":"Unified Canadian Aboriginal Syllabics","script":"Unknown","category":"Lo","kind":"glyph"},{"cp":5596,"name":"CANADIAN SYLLABICS CARRIER THU","block":"Unified Canadian Aboriginal Syllabics","script":"Unknown","category":"Lo","kind":"glyph"},{"cp":5597,"name":"CANADIAN SYLLABICS CARRIER THO","block":"Unified Canadian Aboriginal Syllabics","script":"Unknown","category":"Lo","kind":"glyph"},{"cp":5598,"name":"CANADIAN SYLLABICS CARRIER THE","block":"Unified Canadian Aboriginal Syllabics","script":"Unknown","category":"Lo","kind":"glyph"},{"cp":5599,"name":"CANADIAN SYLLABICS CARRIER THEE","block":"Unified Canadian Aboriginal Syllabics","script":"Unknown","category":"Lo","kind":"glyph"},{"cp":5600,"name":"CANADIAN SYLLABICS CARRIER THI","block":"Unified Canadian Aboriginal Syllabics","script":"Unknown","category":"Lo","kind":"glyph"},{"cp":5601,"name":"CANADIAN SYLLABICS CARRIER THA","block":"Unified Canadian Aboriginal Syllabics","script":"Unknown","category":"Lo","kind":"glyph"},{"cp":5602,"name":"CANADIAN SYLLABICS CARRIER TTU","block":"Unified Canadian Aboriginal Syllabics","script":"Unknown","category":"Lo","kind":"glyph"},{"cp":5603,"name":"CANADIAN SYLLABICS CARRIER TTO","block":"Unified Canadian Aboriginal Syllabics","script":"Unknown","category":"Lo","kind":"glyph"},{"cp":5604,"name":"CANADIAN SYLLABICS CARRIER TTE","block":"Unified Canadian Aboriginal Syllabics","script":"Unknown","category":"Lo","kind":"glyph"},{"cp":5605,"name":"CANADIAN SYLLABICS CARRIER TTEE","block":"Unified Canadian Aboriginal Syllabics","script":"Unknown","category":"Lo","kind":"glyph"},{"cp":5606,"name":"CANADIAN SYLLABICS CARRIER TTI","block":"Unified Canadian Aboriginal Syllabics","script":"Unknown","category":"Lo","kind":"glyph"},{"cp":5607,"name":"CANADIAN SYLLABICS CARRIER TTA","block":"Unified Canadian Aboriginal Syllabics","script":"Unknown","category":"Lo","kind":"glyph"},{"cp":5608,"name":"CANADIAN SYLLABICS CARRIER PU","block":"Unified Canadian Aboriginal Syllabics","script":"Unknown","category":"Lo","kind":"glyph"},{"cp":5609,"name":"CANADIAN SYLLABICS CARRIER PO","block":"Unified Canadian Aboriginal Syllabics","script":"Unknown","category":"Lo","kind":"glyph"},{"cp":5610,"name":"CANADIAN SYLLABICS CARRIER PE","block":"Unified Canadian Aboriginal Syllabics","script":"Unknown","category":"Lo","kind":"glyph"},{"cp":5611,"name":"CANADIAN SYLLABICS CARRIER PEE","block":"Unified Canadian Aboriginal Syllabics","script":"Unknown","category":"Lo","kind":"glyph"},{"cp":5612,"name":"CANADIAN SYLLABICS CARRIER PI","block":"Unified Canadian Aboriginal Syllabics","script":"Unknown","category":"Lo","kind":"glyph"},{"cp":5613,"name":"CANADIAN SYLLABICS CARRIER PA","block":"Unified Canadian Aboriginal Syllabics","script":"Unknown","category":"Lo","kind":"glyph"},{"cp":5614,"name":"CANADIAN SYLLABICS CARRIER P","block":"Unified Canadian Aboriginal Syllabics","script":"Unknown","category":"Lo","kind":"glyph"},{"cp":5615,"name":"CANADIAN SYLLABICS CARRIER GU","block":"Unified Canadian Aboriginal Syllabics","script":"Unknown","category":"Lo","kind":"glyph"},{"cp":5616,"name":"CANADIAN SYLLABICS CARRIER GO","block":"Unified Canadian Aboriginal Syllabics","script":"Unknown","category":"Lo","kind":"glyph"},{"cp":5617,"name":"CANADIAN SYLLABICS CARRIER GE","block":"Unified Canadian Aboriginal Syllabics","script":"Unknown","category":"Lo","kind":"glyph"},{"cp":5618,"name":"CANADIAN SYLLABICS CARRIER GEE","block":"Unified Canadian Aboriginal Syllabics","script":"Unknown","category":"Lo","kind":"glyph"},{"cp":5619,"name":"CANADIAN SYLLABICS CARRIER GI","block":"Unified Canadian Aboriginal Syllabics","script":"Unknown","category":"Lo","kind":"glyph"},{"cp":5620,"name":"CANADIAN SYLLABICS CARRIER GA","block":"Unified Canadian Aboriginal Syllabics","script":"Unknown","category":"Lo","kind":"glyph"},{"cp":5621,"name":"CANADIAN SYLLABICS CARRIER KHU","block":"Unified Canadian Aboriginal Syllabics","script":"Unknown","category":"Lo","kind":"glyph"},{"cp":5622,"name":"CANADIAN SYLLABICS CARRIER KHO","block":"Unified Canadian Aboriginal Syllabics","script":"Unknown","category":"Lo","kind":"glyph"},{"cp":5623,"name":"CANADIAN SYLLABICS CARRIER KHE","block":"Unified Canadian Aboriginal Syllabics","script":"Unknown","category":"Lo","kind":"glyph"},{"cp":5624,"name":"CANADIAN SYLLABICS CARRIER KHEE","block":"Unified Canadian Aboriginal Syllabics","script":"Unknown","category":"Lo","kind":"glyph"},{"cp":5625,"name":"CANADIAN SYLLABICS CARRIER KHI","block":"Unified Canadian Aboriginal Syllabics","script":"Unknown","category":"Lo","kind":"glyph"},{"cp":5626,"name":"CANADIAN SYLLABICS CARRIER KHA","block":"Unified Canadian Aboriginal Syllabics","script":"Unknown","category":"Lo","kind":"glyph"},{"cp":5627,"name":"CANADIAN SYLLABICS CARRIER KKU","block":"Unified Canadian Aboriginal Syllabics","script":"Unknown","category":"Lo","kind":"glyph"},{"cp":5628,"name":"CANADIAN SYLLABICS CARRIER KKO","block":"Unified Canadian Aboriginal Syllabics","script":"Unknown","category":"Lo","kind":"glyph"},{"cp":5629,"name":"CANADIAN SYLLABICS CARRIER KKE","block":"Unified Canadian Aboriginal Syllabics","script":"Unknown","category":"Lo","kind":"glyph"},{"cp":5630,"name":"CANADIAN SYLLABICS CARRIER KKEE","block":"Unified Canadian Aboriginal Syllabics","script":"Unknown","category":"Lo","kind":"glyph"},{"cp":5631,"name":"CANADIAN SYLLABICS CARRIER KKI","block":"Unified Canadian Aboriginal Syllabics","script":"Unknown","category":"Lo","kind":"glyph"},{"cp":5632,"name":"CANADIAN SYLLABICS CARRIER KKA","block":"Unified Canadian Aboriginal Syllabics","script":"Unknown","category":"Lo","kind":"glyph"},{"cp":5633,"name":"CANADIAN SYLLABICS CARRIER KK","block":"Unified Canadian Aboriginal Syllabics","script":"Unknown","category":"Lo","kind":"glyph"},{"cp":5634,"name":"CANADIAN SYLLABICS CARRIER NU","block":"Unified Canadian Aboriginal Syllabics","script":"Unknown","category":"Lo","kind":"glyph"},{"cp":5635,"name":"CANADIAN SYLLABICS CARRIER NO","block":"Unified Canadian Aboriginal Syllabics","script":"Unknown","category":"Lo","kind":"glyph"},{"cp":5636,"name":"CANADIAN SYLLABICS CARRIER NE","block":"Unified Canadian Aboriginal Syllabics","script":"Unknown","category":"Lo","kind":"glyph"},{"cp":5637,"name":"CANADIAN SYLLABICS CARRIER NEE","block":"Unified Canadian Aboriginal Syllabics","script":"Unknown","category":"Lo","kind":"glyph"},{"cp":5638,"name":"CANADIAN SYLLABICS CARRIER NI","block":"Unified Canadian Aboriginal Syllabics","script":"Unknown","category":"Lo","kind":"glyph"},{"cp":5639,"name":"CANADIAN SYLLABICS CARRIER NA","block":"Unified Canadian Aboriginal Syllabics","script":"Unknown","category":"Lo","kind":"glyph"},{"cp":5640,"name":"CANADIAN SYLLABICS CARRIER MU","block":"Unified Canadian Aboriginal Syllabics","script":"Unknown","category":"Lo","kind":"glyph"},{"cp":5641,"name":"CANADIAN SYLLABICS CARRIER MO","block":"Unified Canadian Aboriginal Syllabics","script":"Unknown","category":"Lo","kind":"glyph"},{"cp":5642,"name":"CANADIAN SYLLABICS CARRIER ME","block":"Unified Canadian Aboriginal Syllabics","script":"Unknown","category":"Lo","kind":"glyph"},{"cp":5643,"name":"CANADIAN SYLLABICS CARRIER MEE","block":"Unified Canadian Aboriginal Syllabics","script":"Unknown","category":"Lo","kind":"glyph"},{"cp":5644,"name":"CANADIAN SYLLABICS CARRIER MI","block":"Unified Canadian Aboriginal Syllabics","script":"Unknown","category":"Lo","kind":"glyph"},{"cp":5645,"name":"CANADIAN SYLLABICS CARRIER MA","block":"Unified Canadian Aboriginal Syllabics","script":"Unknown","category":"Lo","kind":"glyph"},{"cp":5646,"name":"CANADIAN SYLLABICS CARRIER YU","block":"Unified Canadian Aboriginal Syllabics","script":"Unknown","category":"Lo","kind":"glyph"},{"cp":5647,"name":"CANADIAN SYLLABICS CARRIER YO","block":"Unified Canadian Aboriginal Syllabics","script":"Unknown","category":"Lo","kind":"glyph"},{"cp":5648,"name":"CANADIAN SYLLABICS CARRIER YE","block":"Unified Canadian Aboriginal Syllabics","script":"Unknown","category":"Lo","kind":"glyph"},{"cp":5649,"name":"CANADIAN SYLLABICS CARRIER YEE","block":"Unified Canadian Aboriginal Syllabics","script":"Unknown","category":"Lo","kind":"glyph"},{"cp":5650,"name":"CANADIAN SYLLABICS CARRIER YI","block":"Unified Canadian Aboriginal Syllabics","script":"Unknown","category":"Lo","kind":"glyph"},{"cp":5651,"name":"CANADIAN SYLLABICS CARRIER YA","block":"Unified Canadian Aboriginal Syllabics","script":"Unknown","category":"Lo","kind":"glyph"},{"cp":5652,"name":"CANADIAN SYLLABICS CARRIER JU","block":"Unified Canadian Aboriginal Syllabics","script":"Unknown","category":"Lo","kind":"glyph"},{"cp":5653,"name":"CANADIAN SYLLABICS SAYISI JU","block":"Unified Canadian Aboriginal Syllabics","script":"Unknown","category":"Lo","kind":"glyph"},{"cp":5654,"name":"CANADIAN SYLLABICS CARRIER JO","block":"Unified Canadian Aboriginal Syllabics","script":"Unknown","category":"Lo","kind":"glyph"},{"cp":5655,"name":"CANADIAN SYLLABICS CARRIER JE","block":"Unified Canadian Aboriginal Syllabics","script":"Unknown","category":"Lo","kind":"glyph"},{"cp":5656,"name":"CANADIAN SYLLABICS CARRIER JEE","block":"Unified Canadian Aboriginal Syllabics","script":"Unknown","category":"Lo","kind":"glyph"},{"cp":5657,"name":"CANADIAN SYLLABICS CARRIER JI","block":"Unified Canadian Aboriginal Syllabics","script":"Unknown","category":"Lo","kind":"glyph"},{"cp":5658,"name":"CANADIAN SYLLABICS SAYISI JI","block":"Unified Canadian Aboriginal Syllabics","script":"Unknown","category":"Lo","kind":"glyph"},{"cp":5659,"name":"CANADIAN SYLLABICS CARRIER JA","block":"Unified Canadian Aboriginal Syllabics","script":"Unknown","category":"Lo","kind":"glyph"},{"cp":5660,"name":"CANADIAN SYLLABICS CARRIER JJU","block":"Unified Canadian Aboriginal Syllabics","script":"Unknown","category":"Lo","kind":"glyph"},{"cp":5661,"name":"CANADIAN SYLLABICS CARRIER JJO","block":"Unified Canadian Aboriginal Syllabics","script":"Unknown","category":"Lo","kind":"glyph"},{"cp":5662,"name":"CANADIAN SYLLABICS CARRIER JJE","block":"Unified Canadian Aboriginal Syllabics","script":"Unknown","category":"Lo","kind":"glyph"},{"cp":5663,"name":"CANADIAN SYLLABICS CARRIER JJEE","block":"Unified Canadian Aboriginal Syllabics","script":"Unknown","category":"Lo","kind":"glyph"},{"cp":5664,"name":"CANADIAN SYLLABICS CARRIER JJI","block":"Unified Canadian Aboriginal Syllabics","script":"Unknown","category":"Lo","kind":"glyph"},{"cp":5665,"name":"CANADIAN SYLLABICS CARRIER JJA","block":"Unified Canadian Aboriginal Syllabics","script":"Unknown","category":"Lo","kind":"glyph"},{"cp":5666,"name":"CANADIAN SYLLABICS CARRIER LU","block":"Unified Canadian Aboriginal Syllabics","script":"Unknown","category":"Lo","kind":"glyph"},{"cp":5667,"name":"CANADIAN SYLLABICS CARRIER LO","block":"Unified Canadian Aboriginal Syllabics","script":"Unknown","category":"Lo","kind":"glyph"},{"cp":5668,"name":"CANADIAN SYLLABICS CARRIER LE","block":"Unified Canadian Aboriginal Syllabics","script":"Unknown","category":"Lo","kind":"glyph"},{"cp":5669,"name":"CANADIAN SYLLABICS CARRIER LEE","block":"Unified Canadian Aboriginal Syllabics","script":"Unknown","category":"Lo","kind":"glyph"},{"cp":5670,"name":"CANADIAN SYLLABICS CARRIER LI","block":"Unified Canadian Aboriginal Syllabics","script":"Unknown","category":"Lo","kind":"glyph"},{"cp":5671,"name":"CANADIAN SYLLABICS CARRIER LA","block":"Unified Canadian Aboriginal Syllabics","script":"Unknown","category":"Lo","kind":"glyph"},{"cp":5672,"name":"CANADIAN SYLLABICS CARRIER DLU","block":"Unified Canadian Aboriginal Syllabics","script":"Unknown","category":"Lo","kind":"glyph"},{"cp":5673,"name":"CANADIAN SYLLABICS CARRIER DLO","block":"Unified Canadian Aboriginal Syllabics","script":"Unknown","category":"Lo","kind":"glyph"},{"cp":5674,"name":"CANADIAN SYLLABICS CARRIER DLE","block":"Unified Canadian Aboriginal Syllabics","script":"Unknown","category":"Lo","kind":"glyph"},{"cp":5675,"name":"CANADIAN SYLLABICS CARRIER DLEE","block":"Unified Canadian Aboriginal Syllabics","script":"Unknown","category":"Lo","kind":"glyph"},{"cp":5676,"name":"CANADIAN SYLLABICS CARRIER DLI","block":"Unified Canadian Aboriginal Syllabics","script":"Unknown","category":"Lo","kind":"glyph"},{"cp":5677,"name":"CANADIAN SYLLABICS CARRIER DLA","block":"Unified Canadian Aboriginal Syllabics","script":"Unknown","category":"Lo","kind":"glyph"},{"cp":5678,"name":"CANADIAN SYLLABICS CARRIER LHU","block":"Unified Canadian Aboriginal Syllabics","script":"Unknown","category":"Lo","kind":"glyph"},{"cp":5679,"name":"CANADIAN SYLLABICS CARRIER LHO","block":"Unified Canadian Aboriginal Syllabics","script":"Unknown","category":"Lo","kind":"glyph"},{"cp":5680,"name":"CANADIAN SYLLABICS CARRIER LHE","block":"Unified Canadian Aboriginal Syllabics","script":"Unknown","category":"Lo","kind":"glyph"},{"cp":5681,"name":"CANADIAN SYLLABICS CARRIER LHEE","block":"Unified Canadian Aboriginal Syllabics","script":"Unknown","category":"Lo","kind":"glyph"},{"cp":5682,"name":"CANADIAN SYLLABICS CARRIER LHI","block":"Unified Canadian Aboriginal Syllabics","script":"Unknown","category":"Lo","kind":"glyph"},{"cp":5683,"name":"CANADIAN SYLLABICS CARRIER LHA","block":"Unified Canadian Aboriginal Syllabics","script":"Unknown","category":"Lo","kind":"glyph"},{"cp":5684,"name":"CANADIAN SYLLABICS CARRIER TLHU","block":"Unified Canadian Aboriginal Syllabics","script":"Unknown","category":"Lo","kind":"glyph"},{"cp":5685,"name":"CANADIAN SYLLABICS CARRIER TLHO","block":"Unified Canadian Aboriginal Syllabics","script":"Unknown","category":"Lo","kind":"glyph"},{"cp":5686,"name":"CANADIAN SYLLABICS CARRIER TLHE","block":"Unified Canadian Aboriginal Syllabics","script":"Unknown","category":"Lo","kind":"glyph"},{"cp":5687,"name":"CANADIAN SYLLABICS CARRIER TLHEE","block":"Unified Canadian Aboriginal Syllabics","script":"Unknown","category":"Lo","kind":"glyph"},{"cp":5688,"name":"CANADIAN SYLLABICS CARRIER TLHI","block":"Unified Canadian Aboriginal Syllabics","script":"Unknown","category":"Lo","kind":"glyph"},{"cp":5689,"name":"CANADIAN SYLLABICS CARRIER TLHA","block":"Unified Canadian Aboriginal Syllabics","script":"Unknown","category":"Lo","kind":"glyph"},{"cp":5690,"name":"CANADIAN SYLLABICS CARRIER TLU","block":"Unified Canadian Aboriginal Syllabics","script":"Unknown","category":"Lo","kind":"glyph"},{"cp":5691,"name":"CANADIAN SYLLABICS CARRIER TLO","block":"Unified Canadian Aboriginal Syllabics","script":"Unknown","category":"Lo","kind":"glyph"},{"cp":5692,"name":"CANADIAN SYLLABICS CARRIER TLE","block":"Unified Canadian Aboriginal Syllabics","script":"Unknown","category":"Lo","kind":"glyph"},{"cp":5693,"name":"CANADIAN SYLLABICS CARRIER TLEE","block":"Unified Canadian Aboriginal Syllabics","script":"Unknown","category":"Lo","kind":"glyph"},{"cp":5694,"name":"CANADIAN SYLLABICS CARRIER TLI","block":"Unified Canadian Aboriginal Syllabics","script":"Unknown","category":"Lo","kind":"glyph"},{"cp":5695,"name":"CANADIAN SYLLABICS CARRIER TLA","block":"Unified Canadian Aboriginal Syllabics","script":"Unknown","category":"Lo","kind":"glyph"},{"cp":5696,"name":"CANADIAN SYLLABICS CARRIER ZU","block":"Unified Canadian Aboriginal Syllabics","script":"Unknown","category":"Lo","kind":"glyph"},{"cp":5697,"name":"CANADIAN SYLLABICS CARRIER ZO","block":"Unified Canadian Aboriginal Syllabics","script":"Unknown","category":"Lo","kind":"glyph"},{"cp":5698,"name":"CANADIAN SYLLABICS CARRIER ZE","block":"Unified Canadian Aboriginal Syllabics","script":"Unknown","category":"Lo","kind":"glyph"},{"cp":5699,"name":"CANADIAN SYLLABICS CARRIER ZEE","block":"Unified Canadian Aboriginal Syllabics","script":"Unknown","category":"Lo","kind":"glyph"},{"cp":5700,"name":"CANADIAN SYLLABICS CARRIER ZI","block":"Unified Canadian Aboriginal Syllabics","script":"Unknown","category":"Lo","kind":"glyph"},{"cp":5701,"name":"CANADIAN SYLLABICS CARRIER ZA","block":"Unified Canadian Aboriginal Syllabics","script":"Unknown","category":"Lo","kind":"glyph"},{"cp":5702,"name":"CANADIAN SYLLABICS CARRIER Z","block":"Unified Canadian Aboriginal Syllabics","script":"Unknown","category":"Lo","kind":"glyph"},{"cp":5703,"name":"CANADIAN SYLLABICS CARRIER INITIAL Z","block":"Unified Canadian Aboriginal Syllabics","script":"Unknown","category":"Lo","kind":"glyph"},{"cp":5704,"name":"CANADIAN SYLLABICS CARRIER DZU","block":"Unified Canadian Aboriginal Syllabics","script":"Unknown","category":"Lo","kind":"glyph"},{"cp":5705,"name":"CANADIAN SYLLABICS CARRIER DZO","block":"Unified Canadian Aboriginal Syllabics","script":"Unknown","category":"Lo","kind":"glyph"},{"cp":5706,"name":"CANADIAN SYLLABICS CARRIER DZE","block":"Unified Canadian Aboriginal Syllabics","script":"Unknown","category":"Lo","kind":"glyph"},{"cp":5707,"name":"CANADIAN SYLLABICS CARRIER DZEE","block":"Unified Canadian Aboriginal Syllabics","script":"Unknown","category":"Lo","kind":"glyph"},{"cp":5708,"name":"CANADIAN SYLLABICS CARRIER DZI","block":"Unified Canadian Aboriginal Syllabics","script":"Unknown","category":"Lo","kind":"glyph"},{"cp":5709,"name":"CANADIAN SYLLABICS CARRIER DZA","block":"Unified Canadian Aboriginal Syllabics","script":"Unknown","category":"Lo","kind":"glyph"},{"cp":5710,"name":"CANADIAN SYLLABICS CARRIER SU","block":"Unified Canadian Aboriginal Syllabics","script":"Unknown","category":"Lo","kind":"glyph"},{"cp":5711,"name":"CANADIAN SYLLABICS CARRIER SO","block":"Unified Canadian Aboriginal Syllabics","script":"Unknown","category":"Lo","kind":"glyph"},{"cp":5712,"name":"CANADIAN SYLLABICS CARRIER SE","block":"Unified Canadian Aboriginal Syllabics","script":"Unknown","category":"Lo","kind":"glyph"},{"cp":5713,"name":"CANADIAN SYLLABICS CARRIER SEE","block":"Unified Canadian Aboriginal Syllabics","script":"Unknown","category":"Lo","kind":"glyph"},{"cp":5714,"name":"CANADIAN SYLLABICS CARRIER SI","block":"Unified Canadian Aboriginal Syllabics","script":"Unknown","category":"Lo","kind":"glyph"},{"cp":5715,"name":"CANADIAN SYLLABICS CARRIER SA","block":"Unified Canadian Aboriginal Syllabics","script":"Unknown","category":"Lo","kind":"glyph"},{"cp":5716,"name":"CANADIAN SYLLABICS CARRIER SHU","block":"Unified Canadian Aboriginal Syllabics","script":"Unknown","category":"Lo","kind":"glyph"},{"cp":5717,"name":"CANADIAN SYLLABICS CARRIER SHO","block":"Unified Canadian Aboriginal Syllabics","script":"Unknown","category":"Lo","kind":"glyph"},{"cp":5718,"name":"CANADIAN SYLLABICS CARRIER SHE","block":"Unified Canadian Aboriginal Syllabics","script":"Unknown","category":"Lo","kind":"glyph"},{"cp":5719,"name":"CANADIAN SYLLABICS CARRIER SHEE","block":"Unified Canadian Aboriginal Syllabics","script":"Unknown","category":"Lo","kind":"glyph"},{"cp":5720,"name":"CANADIAN SYLLABICS CARRIER SHI","block":"Unified Canadian Aboriginal Syllabics","script":"Unknown","category":"Lo","kind":"glyph"},{"cp":5721,"name":"CANADIAN SYLLABICS CARRIER SHA","block":"Unified Canadian Aboriginal Syllabics","script":"Unknown","category":"Lo","kind":"glyph"},{"cp":5722,"name":"CANADIAN SYLLABICS CARRIER SH","block":"Unified Canadian Aboriginal Syllabics","script":"Unknown","category":"Lo","kind":"glyph"},{"cp":5723,"name":"CANADIAN SYLLABICS CARRIER TSU","block":"Unified Canadian Aboriginal Syllabics","script":"Unknown","category":"Lo","kind":"glyph"},{"cp":5724,"name":"CANADIAN SYLLABICS CARRIER TSO","block":"Unified Canadian Aboriginal Syllabics","script":"Unknown","category":"Lo","kind":"glyph"},{"cp":5725,"name":"CANADIAN SYLLABICS CARRIER TSE","block":"Unified Canadian Aboriginal Syllabics","script":"Unknown","category":"Lo","kind":"glyph"},{"cp":5726,"name":"CANADIAN SYLLABICS CARRIER TSEE","block":"Unified Canadian Aboriginal Syllabics","script":"Unknown","category":"Lo","kind":"glyph"},{"cp":5727,"name":"CANADIAN SYLLABICS CARRIER TSI","block":"Unified Canadian Aboriginal Syllabics","script":"Unknown","category":"Lo","kind":"glyph"},{"cp":5728,"name":"CANADIAN SYLLABICS CARRIER TSA","block":"Unified Canadian Aboriginal Syllabics","script":"Unknown","category":"Lo","kind":"glyph"},{"cp":5729,"name":"CANADIAN SYLLABICS CARRIER CHU","block":"Unified Canadian Aboriginal Syllabics","script":"Unknown","category":"Lo","kind":"glyph"},{"cp":5730,"name":"CANADIAN SYLLABICS CARRIER CHO","block":"Unified Canadian Aboriginal Syllabics","script":"Unknown","category":"Lo","kind":"glyph"},{"cp":5731,"name":"CANADIAN SYLLABICS CARRIER CHE","block":"Unified Canadian Aboriginal Syllabics","script":"Unknown","category":"Lo","kind":"glyph"},{"cp":5732,"name":"CANADIAN SYLLABICS CARRIER CHEE","block":"Unified Canadian Aboriginal Syllabics","script":"Unknown","category":"Lo","kind":"glyph"},{"cp":5733,"name":"CANADIAN SYLLABICS CARRIER CHI","block":"Unified Canadian Aboriginal Syllabics","script":"Unknown","category":"Lo","kind":"glyph"},{"cp":5734,"name":"CANADIAN SYLLABICS CARRIER CHA","block":"Unified Canadian Aboriginal Syllabics","script":"Unknown","category":"Lo","kind":"glyph"},{"cp":5735,"name":"CANADIAN SYLLABICS CARRIER TTSU","block":"Unified Canadian Aboriginal Syllabics","script":"Unknown","category":"Lo","kind":"glyph"},{"cp":5736,"name":"CANADIAN SYLLABICS CARRIER TTSO","block":"Unified Canadian Aboriginal Syllabics","script":"Unknown","category":"Lo","kind":"glyph"},{"cp":5737,"name":"CANADIAN SYLLABICS CARRIER TTSE","block":"Unified Canadian Aboriginal Syllabics","script":"Unknown","category":"Lo","kind":"glyph"},{"cp":5738,"name":"CANADIAN SYLLABICS CARRIER TTSEE","block":"Unified Canadian Aboriginal Syllabics","script":"Unknown","category":"Lo","kind":"glyph"},{"cp":5739,"name":"CANADIAN SYLLABICS CARRIER TTSI","block":"Unified Canadian Aboriginal Syllabics","script":"Unknown","category":"Lo","kind":"glyph"},{"cp":5740,"name":"CANADIAN SYLLABICS CARRIER TTSA","block":"Unified Canadian Aboriginal Syllabics","script":"Unknown","category":"Lo","kind":"glyph"},{"cp":5741,"name":"CANADIAN SYLLABICS CHI SIGN","block":"Unified Canadian Aboriginal Syllabics","script":"Unknown","category":"So","kind":"glyph"},{"cp":5742,"name":"CANADIAN SYLLABICS FULL STOP","block":"Unified Canadian Aboriginal Syllabics","script":"Unknown","category":"Po","kind":"glyph"},{"cp":5743,"name":"CANADIAN SYLLABICS QAI","block":"Unified Canadian Aboriginal Syllabics","script":"Unknown","category":"Lo","kind":"glyph"},{"cp":5744,"name":"CANADIAN SYLLABICS NGAI","block":"Unified Canadian Aboriginal Syllabics","script":"Unknown","category":"Lo","kind":"glyph"},{"cp":5745,"name":"CANADIAN SYLLABICS NNGI","block":"Unified Canadian Aboriginal Syllabics","script":"Unknown","category":"Lo","kind":"glyph"},{"cp":5746,"name":"CANADIAN SYLLABICS NNGII","block":"Unified Canadian Aboriginal Syllabics","script":"Unknown","category":"Lo","kind":"glyph"},{"cp":5747,"name":"CANADIAN SYLLABICS NNGO","block":"Unified Canadian Aboriginal Syllabics","script":"Unknown","category":"Lo","kind":"glyph"},{"cp":5748,"name":"CANADIAN SYLLABICS NNGOO","block":"Unified Canadian Aboriginal Syllabics","script":"Unknown","category":"Lo","kind":"glyph"},{"cp":5749,"name":"CANADIAN SYLLABICS NNGA","block":"Unified Canadian Aboriginal Syllabics","script":"Unknown","category":"Lo","kind":"glyph"},{"cp":5750,"name":"CANADIAN SYLLABICS NNGAA","block":"Unified Canadian Aboriginal Syllabics","script":"Unknown","category":"Lo","kind":"glyph"},{"cp":5751,"name":"CANADIAN SYLLABICS WOODS-CREE THWEE","block":"Unified Canadian Aboriginal Syllabics","script":"Unknown","category":"Lo","kind":"glyph"},{"cp":5752,"name":"CANADIAN SYLLABICS WOODS-CREE THWI","block":"Unified Canadian Aboriginal Syllabics","script":"Unknown","category":"Lo","kind":"glyph"},{"cp":5753,"name":"CANADIAN SYLLABICS WOODS-CREE THWII","block":"Unified Canadian Aboriginal Syllabics","script":"Unknown","category":"Lo","kind":"glyph"},{"cp":5754,"name":"CANADIAN SYLLABICS WOODS-CREE THWO","block":"Unified Canadian Aboriginal Syllabics","script":"Unknown","category":"Lo","kind":"glyph"},{"cp":5755,"name":"CANADIAN SYLLABICS WOODS-CREE THWOO","block":"Unified Canadian Aboriginal Syllabics","script":"Unknown","category":"Lo","kind":"glyph"},{"cp":5756,"name":"CANADIAN SYLLABICS WOODS-CREE THWA","block":"Unified Canadian Aboriginal Syllabics","script":"Unknown","category":"Lo","kind":"glyph"},{"cp":5757,"name":"CANADIAN SYLLABICS WOODS-CREE THWAA","block":"Unified Canadian Aboriginal Syllabics","script":"Unknown","category":"Lo","kind":"glyph"},{"cp":5758,"name":"CANADIAN SYLLABICS WOODS-CREE FINAL TH","block":"Unified Canadian Aboriginal Syllabics","script":"Unknown","category":"Lo","kind":"glyph"},{"cp":5759,"name":"CANADIAN SYLLABICS BLACKFOOT W","block":"Unified Canadian Aboriginal Syllabics","script":"Unknown","category":"Lo","kind":"glyph"}]
